{"last_update": "2026-02-25 17:00:00 WIB (Backfilled)", "super_screener": [{"Ticker": "JAYA", "Signal_Date": "2026-02-25", "Bars_Ago": 0, "Open": 131, "Close": 162, "Pct_Change_Price": 35.0, "Volume": 269728100, "Volume_Spike": true, "KO": 553623895.84, "UT_Buy": false, "ST_Trend": 1, "Aroon_Up": 100.0, "UT_Pos": 1, "PSAR_Trend": "Bull", "Kernel_Color": "\ud83d\udfe2", "Kernel_Flip": "\u274c Tidak", "Pattern_Label": "POP_CEPAT", "PER": "N/A", "PBV": "N/A"}, {"Ticker": "KAQI", "Signal_Date": "2026-02-25", "Bars_Ago": 0, "Open": 79, "Close": 105, "Pct_Change_Price": 34.62, "Volume": 1502052800, "Volume_Spike": true, "KO": 3011835956.13, "UT_Buy": true, "ST_Trend": 1, "Aroon_Up": 100.0, "UT_Pos": 1, "PSAR_Trend": "Bull", "Kernel_Color": "\ud83d\udfe2", "Kernel_Flip": "\u2705 Ya", "Pattern_Label": "POP_CEPAT", "PER": "N/A", "PBV": "N/A"}, {"Ticker": "OMED", "Signal_Date": "2026-02-25", "Bars_Ago": 0, "Open": 216, "Close": 242, "Pct_Change_Price": 12.04, "Volume": 17690400, "Volume_Spike": true, "KO": 42877962.63, "UT_Buy": false, "ST_Trend": 1, "Aroon_Up": 100.0, "UT_Pos": 1, "PSAR_Trend": "Bull", "Kernel_Color": "\ud83d\udfe2", "Kernel_Flip": "\u274c Tidak", "Pattern_Label": "POP_CEPAT", "PER": "N/A", "PBV": "N/A"}, {"Ticker": "KLBF", "Signal_Date": "2026-02-25", "Bars_Ago": 0, "Open": 1075, "Close": 1115, "Pct_Change_Price": 5.19, "Volume": 78710500, "Volume_Spike": false, "KO": 299901318.77, "UT_Buy": true, "ST_Trend": -1, "Aroon_Up": 100.0, "UT_Pos": 1, "PSAR_Trend": "Bull", "Kernel_Color": "\ud83d\udd34", "Kernel_Flip": "\u274c Tidak", "Pattern_Label": "NOISE_TRAP", "PER": "N/A", "PBV": "N/A"}, {"Ticker": "SPMA", "Signal_Date": "2026-02-25", "Bars_Ago": 0, "Open": 230, "Close": 238, "Pct_Change_Price": 3.48, "Volume": 1336600, "Volume_Spike": false, "KO": -3762366.32, "UT_Buy": true, "ST_Trend": -1, "Aroon_Up": 100.0, "UT_Pos": 1, "PSAR_Trend": "Bear", "Kernel_Color": "\ud83d\udfe2", "Kernel_Flip": "\u2705 Ya", "Pattern_Label": "NOISE_TRAP", "PER": "N/A", "PBV": 1.79}], "aroon_ut": [{"Ticker": "KAQI", "Signal_Date": "2026-02-25", "Bars_Ago": 0, "Open": 79, "Close": 105, "Pct_Change_Price": 34.62, "Volume": 1502052800, "Volume_Spike": true, "KO": 3011835956.13, "UT_Buy": true, "ST_Trend": 1, "Aroon_Up": 100.0, "UT_Pos": 1, "PSAR_Trend": "Bull", "Kernel_Color": "\ud83d\udfe2", "Kernel_Flip": "\u2705 Ya", "Pattern_Label": "POP_CEPAT", "PER": "N/A", "PBV": "N/A"}, {"Ticker": "SOHO", "Signal_Date": "2026-02-25", "Bars_Ago": 0, "Open": 2850, "Close": 3110, "Pct_Change_Price": 15.19, "Volume": 3224600, "Volume_Spike": true, "KO": 7763826.85, "UT_Buy": true, "ST_Trend": -1, "Aroon_Up": 100.0, "UT_Pos": 1, "PSAR_Trend": "Bull", "Kernel_Color": "\ud83d\udfe2", "Kernel_Flip": "\u2705 Ya", "Pattern_Label": "POP_CEPAT", "PER": "N/A", "PBV": "N/A"}, {"Ticker": "KLBF", "Signal_Date": "2026-02-25", "Bars_Ago": 0, "Open": 1075, "Close": 1115, "Pct_Change_Price": 5.19, "Volume": 78710500, "Volume_Spike": false, "KO": 299901318.77, "UT_Buy": true, "ST_Trend": -1, "Aroon_Up": 100.0, "UT_Pos": 1, "PSAR_Trend": "Bull", "Kernel_Color": "\ud83d\udd34", "Kernel_Flip": "\u274c Tidak", "Pattern_Label": "NOISE_TRAP", "PER": "N/A", "PBV": "N/A"}, {"Ticker": "SPMA", "Signal_Date": "2026-02-25", "Bars_Ago": 0, "Open": 230, "Close": 238, "Pct_Change_Price": 3.48, "Volume": 1336600, "Volume_Spike": false, "KO": -3762366.32, "UT_Buy": true, "ST_Trend": -1, "Aroon_Up": 100.0, "UT_Pos": 1, "PSAR_Trend": "Bear", "Kernel_Color": "\ud83d\udfe2", "Kernel_Flip": "\u2705 Ya", "Pattern_Label": "NOISE_TRAP", "PER": "N/A", "PBV": 1.79}, {"Ticker": "LPGI", "Signal_Date": "2026-02-25", "Bars_Ago": 0, "Open": 650, "Close": 660, "Pct_Change_Price": 3.12, "Volume": 98300, "Volume_Spike": false, "KO": -858557.53, "UT_Buy": true, "ST_Trend": -1, "Aroon_Up": 100.0, "UT_Pos": 1, "PSAR_Trend": "Bear", "Kernel_Color": "\ud83d\udfe2", "Kernel_Flip": "\u274c Tidak", "Pattern_Label": "NOISE_TRAP", "PER": "N/A", "PBV": "N/A"}], "ko_ut_vol": [{"Ticker": "SCNP", "Signal_Date": "2026-02-25", "Bars_Ago": 0, "Open": 174, "Close": 224, "Pct_Change_Price": 34.94, "Volume": 28854100, "Volume_Spike": true, "KO": 53912748.77, "UT_Buy": true, "ST_Trend": -1, "Aroon_Up": 0.0, "UT_Pos": 1, "PSAR_Trend": "Bear", "Kernel_Color": "\ud83d\udfe2", "Kernel_Flip": "\u2705 Ya", "Pattern_Label": "POP_CEPAT", "PER": "N/A", "PBV": "N/A"}, {"Ticker": "KAQI", "Signal_Date": "2026-02-25", "Bars_Ago": 0, "Open": 79, "Close": 105, "Pct_Change_Price": 34.62, "Volume": 1502052800, "Volume_Spike": true, "KO": 3011835956.13, "UT_Buy": true, "ST_Trend": 1, "Aroon_Up": 100.0, "UT_Pos": 1, "PSAR_Trend": "Bull", "Kernel_Color": "\ud83d\udfe2", "Kernel_Flip": "\u2705 Ya", "Pattern_Label": "POP_CEPAT", "PER": "N/A", "PBV": "N/A"}, {"Ticker": "ASLI", "Signal_Date": "2026-02-25", "Bars_Ago": 0, "Open": 364, "Close": 450, "Pct_Change_Price": 22.95, "Volume": 180836600, "Volume_Spike": true, "KO": -494261499.85, "UT_Buy": true, "ST_Trend": -1, "Aroon_Up": 0.0, "UT_Pos": 1, "PSAR_Trend": "Bull", "Kernel_Color": "\ud83d\udd34", "Kernel_Flip": "\u274c Tidak", "Pattern_Label": "POP_CEPAT", "PER": "N/A", "PBV": "N/A"}, {"Ticker": "SOHO", "Signal_Date": "2026-02-25", "Bars_Ago": 0, "Open": 2850, "Close": 3110, "Pct_Change_Price": 15.19, "Volume": 3224600, "Volume_Spike": true, "KO": 7763826.85, "UT_Buy": true, "ST_Trend": -1, "Aroon_Up": 100.0, "UT_Pos": 1, "PSAR_Trend": "Bull", "Kernel_Color": "\ud83d\udfe2", "Kernel_Flip": "\u2705 Ya", "Pattern_Label": "POP_CEPAT", "PER": "N/A", "PBV": "N/A"}, {"Ticker": "HEAL", "Signal_Date": "2026-02-25", "Bars_Ago": 0, "Open": 1295, "Close": 1350, "Pct_Change_Price": 4.65, "Volume": 17661100, "Volume_Spike": true, "KO": 47897619.82, "UT_Buy": true, "ST_Trend": -1, "Aroon_Up": 0.0, "UT_Pos": 1, "PSAR_Trend": "Bull", "Kernel_Color": "\ud83d\udfe2", "Kernel_Flip": "\u2705 Ya", "Pattern_Label": "NOISE_TRAP", "PER": 30.66, "PBV": "N/A"}, {"Ticker": "KLBF", "Signal_Date": "2026-02-25", "Bars_Ago": 0, "Open": 1075, "Close": 1115, "Pct_Change_Price": 5.19, "Volume": 78710500, "Volume_Spike": false, "KO": 299901318.77, "UT_Buy": true, "ST_Trend": -1, "Aroon_Up": 100.0, "UT_Pos": 1, "PSAR_Trend": "Bull", "Kernel_Color": "\ud83d\udd34", "Kernel_Flip": "\u274c Tidak", "Pattern_Label": "NOISE_TRAP", "PER": "N/A", "PBV": "N/A"}, {"Ticker": "SPMA", "Signal_Date": "2026-02-25", "Bars_Ago": 0, "Open": 230, "Close": 238, "Pct_Change_Price": 3.48, "Volume": 1336600, "Volume_Spike": false, "KO": -3762366.32, "UT_Buy": true, "ST_Trend": -1, "Aroon_Up": 100.0, "UT_Pos": 1, "PSAR_Trend": "Bear", "Kernel_Color": "\ud83d\udfe2", "Kernel_Flip": "\u2705 Ya", "Pattern_Label": "NOISE_TRAP", "PER": "N/A", "PBV": 1.79}], "aroon_psar": [{"Ticker": "JAYA", "Signal_Date": "2026-02-25", "Bars_Ago": 0, "Open": 131, "Close": 162, "Pct_Change_Price": 35.0, "Volume": 269728100, "Volume_Spike": true, "KO": 553623895.84, "UT_Buy": false, "ST_Trend": 1, "Aroon_Up": 100.0, "UT_Pos": 1, "PSAR_Trend": "Bull", "Kernel_Color": "\ud83d\udfe2", "Kernel_Flip": "\u274c Tidak", "Pattern_Label": "POP_CEPAT", "PER": "N/A", "PBV": "N/A"}, {"Ticker": "KAQI", "Signal_Date": "2026-02-25", "Bars_Ago": 0, "Open": 79, "Close": 105, "Pct_Change_Price": 34.62, "Volume": 1502052800, "Volume_Spike": true, "KO": 3011835956.13, "UT_Buy": true, "ST_Trend": 1, "Aroon_Up": 100.0, "UT_Pos": 1, "PSAR_Trend": "Bull", "Kernel_Color": "\ud83d\udfe2", "Kernel_Flip": "\u2705 Ya", "Pattern_Label": "POP_CEPAT", "PER": "N/A", "PBV": "N/A"}, {"Ticker": "SOHO", "Signal_Date": "2026-02-25", "Bars_Ago": 0, "Open": 2850, "Close": 3110, "Pct_Change_Price": 15.19, "Volume": 3224600, "Volume_Spike": true, "KO": 7763826.85, "UT_Buy": true, "ST_Trend": -1, "Aroon_Up": 100.0, "UT_Pos": 1, "PSAR_Trend": "Bull", "Kernel_Color": "\ud83d\udfe2", "Kernel_Flip": "\u2705 Ya", "Pattern_Label": "POP_CEPAT", "PER": "N/A", "PBV": "N/A"}, {"Ticker": "OMED", "Signal_Date": "2026-02-25", "Bars_Ago": 0, "Open": 216, "Close": 242, "Pct_Change_Price": 12.04, "Volume": 17690400, "Volume_Spike": true, "KO": 42877962.63, "UT_Buy": false, "ST_Trend": 1, "Aroon_Up": 100.0, "UT_Pos": 1, "PSAR_Trend": "Bull", "Kernel_Color": "\ud83d\udfe2", "Kernel_Flip": "\u274c Tidak", "Pattern_Label": "POP_CEPAT", "PER": "N/A", "PBV": "N/A"}, {"Ticker": "LUCK", "Signal_Date": "2026-02-25", "Bars_Ago": 0, "Open": 124, "Close": 117, "Pct_Change_Price": 0.86, "Volume": 11838700, "Volume_Spike": true, "KO": -470110148.46, "UT_Buy": false, "ST_Trend": -1, "Aroon_Up": 100.0, "UT_Pos": -1, "PSAR_Trend": "Bull", "Kernel_Color": "\ud83d\udd34", "Kernel_Flip": "\u274c Tidak", "Pattern_Label": "NOISE_TRAP", "PER": 30.53, "PBV": -2.74}, {"Ticker": "WGSH", "Signal_Date": "2026-02-25", "Bars_Ago": 0, "Open": 148, "Close": 125, "Pct_Change_Price": -8.76, "Volume": 5121400, "Volume_Spike": true, "KO": -28655638.7, "UT_Buy": false, "ST_Trend": -1, "Aroon_Up": 100.0, "UT_Pos": -1, "PSAR_Trend": "Bull", "Kernel_Color": "\ud83d\udd34", "Kernel_Flip": "\u274c Tidak", "Pattern_Label": "NOISE_TRAP", "PER": "N/A", "PBV": "N/A"}, {"Ticker": "KLBF", "Signal_Date": "2026-02-25", "Bars_Ago": 0, "Open": 1075, "Close": 1115, "Pct_Change_Price": 5.19, "Volume": 78710500, "Volume_Spike": false, "KO": 299901318.77, "UT_Buy": true, "ST_Trend": -1, "Aroon_Up": 100.0, "UT_Pos": 1, "PSAR_Trend": "Bull", "Kernel_Color": "\ud83d\udd34", "Kernel_Flip": "\u274c Tidak", "Pattern_Label": "NOISE_TRAP", "PER": "N/A", "PBV": "N/A"}, {"Ticker": "GPRA", "Signal_Date": "2026-02-25", "Bars_Ago": 0, "Open": 118, "Close": 118, "Pct_Change_Price": 0.85, "Volume": 41538700, "Volume_Spike": false, "KO": -234320958.49, "UT_Buy": false, "ST_Trend": -1, "Aroon_Up": 37.5, "UT_Pos": -1, "PSAR_Trend": "Bull", "Kernel_Color": "\ud83d\udd34", "Kernel_Flip": "\u274c Tidak", "Pattern_Label": "NOISE_TRAP", "PER": "N/A", "PBV": "N/A"}, {"Ticker": "IFII", "Signal_Date": "2026-02-25", "Bars_Ago": 0, "Open": 264, "Close": 256, "Pct_Change_Price": 0.79, "Volume": 1337900, "Volume_Spike": false, "KO": -1133323.28, "UT_Buy": false, "ST_Trend": -1, "Aroon_Up": 100.0, "UT_Pos": 1, "PSAR_Trend": "Bull", "Kernel_Color": "\ud83d\udfe2", "Kernel_Flip": "\u274c Tidak", "Pattern_Label": "NOISE_TRAP", "PER": "N/A", "PBV": "N/A"}], "lorentzian_bull": [{"Ticker": "SCNP", "Signal_Date": "2026-02-25", "Bars_Ago": 0, "Open": 174, "Close": 224, "Pct_Change_Price": 34.94, "Volume": 28854100, "Volume_Spike": true, "KO": 53912748.77, "UT_Buy": true, "ST_Trend": -1, "Aroon_Up": 0.0, "UT_Pos": 1, "PSAR_Trend": "Bear", "Kernel_Color": "\ud83d\udfe2", "Kernel_Flip": "\u2705 Ya", "Pattern_Label": "\ud83d\udfe2 Bull (ML: 4)", "PER": "N/A", "PBV": "N/A"}, {"Ticker": "KAQI", "Signal_Date": "2026-02-25", "Bars_Ago": 0, "Open": 79, "Close": 105, "Pct_Change_Price": 34.62, "Volume": 1502052800, "Volume_Spike": true, "KO": 3011835956.13, "UT_Buy": true, "ST_Trend": 1, "Aroon_Up": 100.0, "UT_Pos": 1, "PSAR_Trend": "Bull", "Kernel_Color": "\ud83d\udfe2", "Kernel_Flip": "\u2705 Ya", "Pattern_Label": "\ud83d\udfe2 Bull (ML: 6)", "PER": "N/A", "PBV": "N/A"}, {"Ticker": "CARS", "Signal_Date": "2026-02-25", "Bars_Ago": 0, "Open": 96, "Close": 121, "Pct_Change_Price": 28.72, "Volume": 390840500, "Volume_Spike": true, "KO": 798673500.71, "UT_Buy": false, "ST_Trend": 1, "Aroon_Up": 100.0, "UT_Pos": 1, "PSAR_Trend": "Bull", "Kernel_Color": "\ud83d\udfe2", "Kernel_Flip": "\u2705 Ya", "Pattern_Label": "\ud83d\udfe2 Bull (ML: 5)", "PER": 34.48, "PBV": 1.37}, {"Ticker": "SOHO", "Signal_Date": "2026-02-25", "Bars_Ago": 0, "Open": 2850, "Close": 3110, "Pct_Change_Price": 15.19, "Volume": 3224600, "Volume_Spike": true, "KO": 7763826.85, "UT_Buy": true, "ST_Trend": -1, "Aroon_Up": 100.0, "UT_Pos": 1, "PSAR_Trend": "Bull", "Kernel_Color": "\ud83d\udfe2", "Kernel_Flip": "\u2705 Ya", "Pattern_Label": "\ud83d\udfe2 Bull (ML: 2)", "PER": "N/A", "PBV": "N/A"}, {"Ticker": "AYAM", "Signal_Date": "2026-02-25", "Bars_Ago": 0, "Open": 386, "Close": 410, "Pct_Change_Price": 6.22, "Volume": 91640600, "Volume_Spike": true, "KO": -526979307.91, "UT_Buy": true, "ST_Trend": -1, "Aroon_Up": 100.0, "UT_Pos": 1, "PSAR_Trend": "Bear", "Kernel_Color": "\ud83d\udfe2", "Kernel_Flip": "\u2705 Ya", "Pattern_Label": "\ud83d\udfe2 Bull (ML: -4)", "PER": "N/A", "PBV": "N/A"}, {"Ticker": "BSBK", "Signal_Date": "2026-02-25", "Bars_Ago": 0, "Open": 67, "Close": 71, "Pct_Change_Price": 5.97, "Volume": 1007450500, "Volume_Spike": true, "KO": 576460345.5, "UT_Buy": false, "ST_Trend": -1, "Aroon_Up": 100.0, "UT_Pos": 1, "PSAR_Trend": "Bull", "Kernel_Color": "\ud83d\udfe2", "Kernel_Flip": "\u2705 Ya", "Pattern_Label": "\ud83d\udfe2 Bull (ML: 4)", "PER": 49.88, "PBV": 0.76}, {"Ticker": "DYAN", "Signal_Date": "2026-02-25", "Bars_Ago": 0, "Open": 89, "Close": 93, "Pct_Change_Price": 5.68, "Volume": 18640900, "Volume_Spike": true, "KO": 21008830.84, "UT_Buy": true, "ST_Trend": -1, "Aroon_Up": 100.0, "UT_Pos": 1, "PSAR_Trend": "Bull", "Kernel_Color": "\ud83d\udfe2", "Kernel_Flip": "\u2705 Ya", "Pattern_Label": "\ud83d\udfe2 Bull (ML: 4)", "PER": "N/A", "PBV": "N/A"}, {"Ticker": "HEAL", "Signal_Date": "2026-02-25", "Bars_Ago": 0, "Open": 1295, "Close": 1350, "Pct_Change_Price": 4.65, "Volume": 17661100, "Volume_Spike": true, "KO": 47897619.82, "UT_Buy": true, "ST_Trend": -1, "Aroon_Up": 0.0, "UT_Pos": 1, "PSAR_Trend": "Bull", "Kernel_Color": "\ud83d\udfe2", "Kernel_Flip": "\u2705 Ya", "Pattern_Label": "\ud83d\udfe2 Bull (ML: 1)", "PER": 30.66, "PBV": "N/A"}, {"Ticker": "HATM", "Signal_Date": "2026-02-25", "Bars_Ago": 0, "Open": 332, "Close": 344, "Pct_Change_Price": 3.61, "Volume": 36340500, "Volume_Spike": true, "KO": -160089537.19, "UT_Buy": false, "ST_Trend": -1, "Aroon_Up": 75.0, "UT_Pos": -1, "PSAR_Trend": "Bull", "Kernel_Color": "\ud83d\udfe2", "Kernel_Flip": "\u2705 Ya", "Pattern_Label": "\ud83d\udfe2 Bull (ML: 3)", "PER": "N/A", "PBV": "N/A"}, {"Ticker": "BNII", "Signal_Date": "2026-02-25", "Bars_Ago": 0, "Open": 216, "Close": 220, "Pct_Change_Price": 1.85, "Volume": 4893700, "Volume_Spike": true, "KO": -3419311.84, "UT_Buy": false, "ST_Trend": -1, "Aroon_Up": 0.0, "UT_Pos": 1, "PSAR_Trend": "Bear", "Kernel_Color": "\ud83d\udfe2", "Kernel_Flip": "\u2705 Ya", "Pattern_Label": "\ud83d\udfe2 Bull (ML: 4)", "PER": "N/A", "PBV": "N/A"}, {"Ticker": "ATLA", "Signal_Date": "2026-02-25", "Bars_Ago": 0, "Open": 57, "Close": 57, "Pct_Change_Price": 1.79, "Volume": 168381900, "Volume_Spike": true, "KO": 35765640.33, "UT_Buy": false, "ST_Trend": -1, "Aroon_Up": 75.0, "UT_Pos": 1, "PSAR_Trend": "Bull", "Kernel_Color": "\ud83d\udfe2", "Kernel_Flip": "\u2705 Ya", "Pattern_Label": "\ud83d\udfe2 Bull (ML: 3)", "PER": "N/A", "PBV": "N/A"}, {"Ticker": "KLAS", "Signal_Date": "2026-02-25", "Bars_Ago": 0, "Open": 90, "Close": 91, "Pct_Change_Price": 1.11, "Volume": 107426400, "Volume_Spike": true, "KO": 336849842.84, "UT_Buy": false, "ST_Trend": -1, "Aroon_Up": 100.0, "UT_Pos": 1, "PSAR_Trend": "Bull", "Kernel_Color": "\ud83d\udfe2", "Kernel_Flip": "\u2705 Ya", "Pattern_Label": "\ud83d\udfe2 Bull (ML: 1)", "PER": "N/A", "PBV": "N/A"}, {"Ticker": "IPOL", "Signal_Date": "2026-02-25", "Bars_Ago": 0, "Open": 127, "Close": 126, "Pct_Change_Price": 0.8, "Volume": 3126600, "Volume_Spike": true, "KO": -21736470.51, "UT_Buy": false, "ST_Trend": -1, "Aroon_Up": 12.5, "UT_Pos": -1, "PSAR_Trend": "Bear", "Kernel_Color": "\ud83d\udfe2", "Kernel_Flip": "\u2705 Ya", "Pattern_Label": "\ud83d\udfe2 Bull (ML: 7)", "PER": "N/A", "PBV": "N/A"}, {"Ticker": "BLTA", "Signal_Date": "2026-02-25", "Bars_Ago": 0, "Open": 40, "Close": 44, "Pct_Change_Price": 10.0, "Volume": 8439200, "Volume_Spike": false, "KO": -17407.66, "UT_Buy": true, "ST_Trend": -1, "Aroon_Up": 37.5, "UT_Pos": 1, "PSAR_Trend": "Bull", "Kernel_Color": "\ud83d\udfe2", "Kernel_Flip": "\u2705 Ya", "Pattern_Label": "\ud83d\udfe2 Bull (ML: 1)", "PER": "N/A", "PBV": "N/A"}, {"Ticker": "TAMU", "Signal_Date": "2026-02-25", "Bars_Ago": 0, "Open": 36, "Close": 39, "Pct_Change_Price": 8.33, "Volume": 17497600, "Volume_Spike": false, "KO": 18250694.31, "UT_Buy": true, "ST_Trend": -1, "Aroon_Up": 50.0, "UT_Pos": 1, "PSAR_Trend": "Bull", "Kernel_Color": "\ud83d\udfe2", "Kernel_Flip": "\u2705 Ya", "Pattern_Label": "\ud83d\udfe2 Bull (ML: 0)", "PER": "N/A", "PBV": "N/A"}, {"Ticker": "ASGR", "Signal_Date": "2026-02-25", "Bars_Ago": 0, "Open": 1650, "Close": 1760, "Pct_Change_Price": 8.31, "Volume": 4365500, "Volume_Spike": false, "KO": 1360463.47, "UT_Buy": true, "ST_Trend": -1, "Aroon_Up": 0.0, "UT_Pos": 1, "PSAR_Trend": "Bull", "Kernel_Color": "\ud83d\udfe2", "Kernel_Flip": "\u2705 Ya", "Pattern_Label": "\ud83d\udfe2 Bull (ML: 0)", "PER": "N/A", "PBV": "N/A"}, {"Ticker": "MTFN", "Signal_Date": "2026-02-25", "Bars_Ago": 0, "Open": 27, "Close": 28, "Pct_Change_Price": 7.69, "Volume": 65271200, "Volume_Spike": false, "KO": -734993581.38, "UT_Buy": false, "ST_Trend": -1, "Aroon_Up": 50.0, "UT_Pos": -1, "PSAR_Trend": "Bull", "Kernel_Color": "\ud83d\udfe2", "Kernel_Flip": "\u2705 Ya", "Pattern_Label": "\ud83d\udfe2 Bull (ML: 2)", "PER": "N/A", "PBV": "N/A"}, {"Ticker": "EXCL", "Signal_Date": "2026-02-25", "Bars_Ago": 0, "Open": 3220, "Close": 3360, "Pct_Change_Price": 5.99, "Volume": 50473100, "Volume_Spike": false, "KO": 67385097.53, "UT_Buy": false, "ST_Trend": -1, "Aroon_Up": 100.0, "UT_Pos": 1, "PSAR_Trend": "Bull", "Kernel_Color": "\ud83d\udfe2", "Kernel_Flip": "\u2705 Ya", "Pattern_Label": "\ud83d\udfe2 Bull (ML: -2)", "PER": "N/A", "PBV": -0.05}, {"Ticker": "SLIS", "Signal_Date": "2026-02-25", "Bars_Ago": 0, "Open": 90, "Close": 93, "Pct_Change_Price": 5.68, "Volume": 50613900, "Volume_Spike": false, "KO": -444916321.95, "UT_Buy": false, "ST_Trend": -1, "Aroon_Up": 75.0, "UT_Pos": 1, "PSAR_Trend": "Bull", "Kernel_Color": "\ud83d\udfe2", "Kernel_Flip": "\u2705 Ya", "Pattern_Label": "\ud83d\udfe2 Bull (ML: -1)", "PER": "N/A", "PBV": "N/A"}, {"Ticker": "IBFN", "Signal_Date": "2026-02-25", "Bars_Ago": 0, "Open": 110, "Close": 116, "Pct_Change_Price": 5.45, "Volume": 770000, "Volume_Spike": false, "KO": 13917353.4, "UT_Buy": false, "ST_Trend": -1, "Aroon_Up": 12.5, "UT_Pos": -1, "PSAR_Trend": "Bull", "Kernel_Color": "\ud83d\udfe2", "Kernel_Flip": "\u2705 Ya", "Pattern_Label": "\ud83d\udfe2 Bull (ML: 2)", "PER": "N/A", "PBV": "N/A"}, {"Ticker": "JMAS", "Signal_Date": "2026-02-25", "Bars_Ago": 0, "Open": 234, "Close": 242, "Pct_Change_Price": 4.31, "Volume": 2704100, "Volume_Spike": false, "KO": -73689878.61, "UT_Buy": false, "ST_Trend": -1, "Aroon_Up": 62.5, "UT_Pos": 1, "PSAR_Trend": "Bull", "Kernel_Color": "\ud83d\udfe2", "Kernel_Flip": "\u2705 Ya", "Pattern_Label": "\ud83d\udfe2 Bull (ML: 1)", "PER": "N/A", "PBV": "N/A"}, {"Ticker": "ELTY", "Signal_Date": "2026-02-25", "Bars_Ago": 0, "Open": 47, "Close": 49, "Pct_Change_Price": 4.26, "Volume": 187786300, "Volume_Spike": false, "KO": -2162199948.68, "UT_Buy": false, "ST_Trend": -1, "Aroon_Up": 75.0, "UT_Pos": 1, "PSAR_Trend": "Bull", "Kernel_Color": "\ud83d\udfe2", "Kernel_Flip": "\u2705 Ya", "Pattern_Label": "\ud83d\udfe2 Bull (ML: 1)", "PER": "N/A", "PBV": "N/A"}, {"Ticker": "INET", "Signal_Date": "2026-02-25", "Bars_Ago": 0, "Open": 384, "Close": 396, "Pct_Change_Price": 3.66, "Volume": 426550700, "Volume_Spike": false, "KO": -1182002684.57, "UT_Buy": false, "ST_Trend": -1, "Aroon_Up": 50.0, "UT_Pos": 1, "PSAR_Trend": "Bull", "Kernel_Color": "\ud83d\udfe2", "Kernel_Flip": "\u2705 Ya", "Pattern_Label": "\ud83d\udfe2 Bull (ML: -2)", "PER": "N/A", "PBV": "N/A"}, {"Ticker": "SPMA", "Signal_Date": "2026-02-25", "Bars_Ago": 0, "Open": 230, "Close": 238, "Pct_Change_Price": 3.48, "Volume": 1336600, "Volume_Spike": false, "KO": -3762366.32, "UT_Buy": true, "ST_Trend": -1, "Aroon_Up": 100.0, "UT_Pos": 1, "PSAR_Trend": "Bear", "Kernel_Color": "\ud83d\udfe2", "Kernel_Flip": "\u2705 Ya", "Pattern_Label": "\ud83d\udfe2 Bull (ML: 0)", "PER": "N/A", "PBV": 1.79}, {"Ticker": "PAMG", "Signal_Date": "2026-02-25", "Bars_Ago": 0, "Open": 63, "Close": 66, "Pct_Change_Price": 3.12, "Volume": 6721900, "Volume_Spike": false, "KO": -458611298.69, "UT_Buy": false, "ST_Trend": -1, "Aroon_Up": 37.5, "UT_Pos": 1, "PSAR_Trend": "Bull", "Kernel_Color": "\ud83d\udfe2", "Kernel_Flip": "\u2705 Ya", "Pattern_Label": "\ud83d\udfe2 Bull (ML: 2)", "PER": "N/A", "PBV": "N/A"}, {"Ticker": "BATR", "Signal_Date": "2026-02-25", "Bars_Ago": 0, "Open": 108, "Close": 109, "Pct_Change_Price": 2.83, "Volume": 1431300, "Volume_Spike": false, "KO": -42925850.94, "UT_Buy": false, "ST_Trend": -1, "Aroon_Up": 100.0, "UT_Pos": -1, "PSAR_Trend": "Bull", "Kernel_Color": "\ud83d\udfe2", "Kernel_Flip": "\u2705 Ya", "Pattern_Label": "\ud83d\udfe2 Bull (ML: 3)", "PER": "N/A", "PBV": "N/A"}, {"Ticker": "NIKL", "Signal_Date": "2026-02-25", "Bars_Ago": 0, "Open": 390, "Close": 380, "Pct_Change_Price": 2.7, "Volume": 1571400, "Volume_Spike": false, "KO": -60016906.1, "UT_Buy": false, "ST_Trend": -1, "Aroon_Up": 0.0, "UT_Pos": 1, "PSAR_Trend": "Bear", "Kernel_Color": "\ud83d\udfe2", "Kernel_Flip": "\u2705 Ya", "Pattern_Label": "\ud83d\udfe2 Bull (ML: 2)", "PER": 17.45, "PBV": "N/A"}, {"Ticker": "DOSS", "Signal_Date": "2026-02-25", "Bars_Ago": 0, "Open": 171, "Close": 173, "Pct_Change_Price": 2.37, "Volume": 1227900, "Volume_Spike": false, "KO": -148415229.92, "UT_Buy": false, "ST_Trend": -1, "Aroon_Up": 50.0, "UT_Pos": 1, "PSAR_Trend": "Bull", "Kernel_Color": "\ud83d\udfe2", "Kernel_Flip": "\u2705 Ya", "Pattern_Label": "\ud83d\udfe2 Bull (ML: -2)", "PER": "N/A", "PBV": "N/A"}, {"Ticker": "DATA", "Signal_Date": "2026-02-25", "Bars_Ago": 0, "Open": 3950, "Close": 4020, "Pct_Change_Price": 2.29, "Volume": 1395500, "Volume_Spike": false, "KO": -9736021.27, "UT_Buy": false, "ST_Trend": -1, "Aroon_Up": 75.0, "UT_Pos": 1, "PSAR_Trend": "Bull", "Kernel_Color": "\ud83d\udfe2", "Kernel_Flip": "\u2705 Ya", "Pattern_Label": "\ud83d\udfe2 Bull (ML: 2)", "PER": "N/A", "PBV": "N/A"}, {"Ticker": "TNCA", "Signal_Date": "2026-02-25", "Bars_Ago": 0, "Open": 200, "Close": 204, "Pct_Change_Price": 2.0, "Volume": 606500, "Volume_Spike": false, "KO": -47617231.93, "UT_Buy": false, "ST_Trend": -1, "Aroon_Up": 12.5, "UT_Pos": 1, "PSAR_Trend": "Bull", "Kernel_Color": "\ud83d\udfe2", "Kernel_Flip": "\u2705 Ya", "Pattern_Label": "\ud83d\udfe2 Bull (ML: -2)", "PER": "N/A", "PBV": "N/A"}, {"Ticker": "UANG", "Signal_Date": "2026-02-25", "Bars_Ago": 0, "Open": 4210, "Close": 4210, "Pct_Change_Price": 1.94, "Volume": 815700, "Volume_Spike": false, "KO": -11137090.01, "UT_Buy": false, "ST_Trend": -1, "Aroon_Up": 37.5, "UT_Pos": 1, "PSAR_Trend": "Bull", "Kernel_Color": "\ud83d\udfe2", "Kernel_Flip": "\u2705 Ya", "Pattern_Label": "\ud83d\udfe2 Bull (ML: 2)", "PER": "N/A", "PBV": "N/A"}, {"Ticker": "SEMA", "Signal_Date": "2026-02-25", "Bars_Ago": 0, "Open": 122, "Close": 123, "Pct_Change_Price": 1.65, "Volume": 780500, "Volume_Spike": false, "KO": -36708733.47, "UT_Buy": false, "ST_Trend": -1, "Aroon_Up": 75.0, "UT_Pos": -1, "PSAR_Trend": "Bear", "Kernel_Color": "\ud83d\udfe2", "Kernel_Flip": "\u2705 Ya", "Pattern_Label": "\ud83d\udfe2 Bull (ML: 0)", "PER": "N/A", "PBV": "N/A"}, {"Ticker": "SATU", "Signal_Date": "2026-02-25", "Bars_Ago": 0, "Open": 256, "Close": 260, "Pct_Change_Price": 1.56, "Volume": 3976400, "Volume_Spike": false, "KO": 23267551.67, "UT_Buy": true, "ST_Trend": -1, "Aroon_Up": 25.0, "UT_Pos": 1, "PSAR_Trend": "Bull", "Kernel_Color": "\ud83d\udfe2", "Kernel_Flip": "\u2705 Ya", "Pattern_Label": "\ud83d\udfe2 Bull (ML: -2)", "PER": "N/A", "PBV": "N/A"}, {"Ticker": "JTPE", "Signal_Date": "2026-02-25", "Bars_Ago": 0, "Open": 600, "Close": 605, "Pct_Change_Price": 0.83, "Volume": 1552400, "Volume_Spike": false, "KO": -41664930.89, "UT_Buy": false, "ST_Trend": -1, "Aroon_Up": 12.5, "UT_Pos": -1, "PSAR_Trend": "Bear", "Kernel_Color": "\ud83d\udfe2", "Kernel_Flip": "\u2705 Ya", "Pattern_Label": "\ud83d\udfe2 Bull (ML: 3)", "PER": "N/A", "PBV": "N/A"}, {"Ticker": "DMAS", "Signal_Date": "2026-02-25", "Bars_Ago": 0, "Open": 136, "Close": 137, "Pct_Change_Price": 0.74, "Volume": 31323000, "Volume_Spike": false, "KO": -30289474.42, "UT_Buy": false, "ST_Trend": -1, "Aroon_Up": 0.0, "UT_Pos": 1, "PSAR_Trend": "Bear", "Kernel_Color": "\ud83d\udfe2", "Kernel_Flip": "\u2705 Ya", "Pattern_Label": "\ud83d\udfe2 Bull (ML: 2)", "PER": "N/A", "PBV": "N/A"}], "lorentzian_bear": [{"Ticker": "RBMS", "Signal_Date": "2026-02-25", "Bars_Ago": 0, "Open": 49, "Close": 47, "Pct_Change_Price": -6.0, "Volume": 5341500, "Volume_Spike": true, "KO": -14350999.89, "UT_Buy": false, "ST_Trend": -1, "Aroon_Up": 87.5, "UT_Pos": -1, "PSAR_Trend": "Bull", "Kernel_Color": "\ud83d\udd34", "Kernel_Flip": "\u274c Tidak", "Pattern_Label": "\ud83d\udd34 Bear (ML: -2)", "PER": "N/A", "PBV": "N/A"}, {"Ticker": "ASPR", "Signal_Date": "2026-02-25", "Bars_Ago": 0, "Open": 145, "Close": 133, "Pct_Change_Price": -8.9, "Volume": 90677500, "Volume_Spike": true, "KO": -388239595.35, "UT_Buy": false, "ST_Trend": -1, "Aroon_Up": 50.0, "UT_Pos": -1, "PSAR_Trend": "Bear", "Kernel_Color": "\ud83d\udd34", "Kernel_Flip": "\u274c Tidak", "Pattern_Label": "\ud83d\udd34 Bear (ML: 2)", "PER": "N/A", "PBV": -0.01}, {"Ticker": "MCOR", "Signal_Date": "2026-02-25", "Bars_Ago": 0, "Open": 75, "Close": 75, "Pct_Change_Price": 0.0, "Volume": 10376600, "Volume_Spike": false, "KO": -16043085.47, "UT_Buy": false, "ST_Trend": -1, "Aroon_Up": 0.0, "UT_Pos": 1, "PSAR_Trend": "Bear", "Kernel_Color": "\ud83d\udd34", "Kernel_Flip": "\u274c Tidak", "Pattern_Label": "\ud83d\udd34 Bear (ML: 1)", "PER": "N/A", "PBV": "N/A"}, {"Ticker": "CRAB", "Signal_Date": "2026-02-25", "Bars_Ago": 0, "Open": 248, "Close": 250, "Pct_Change_Price": 0.0, "Volume": 530300, "Volume_Spike": false, "KO": 17660475.89, "UT_Buy": false, "ST_Trend": -1, "Aroon_Up": 87.5, "UT_Pos": -1, "PSAR_Trend": "Bear", "Kernel_Color": "\ud83d\udd34", "Kernel_Flip": "\u274c Tidak", "Pattern_Label": "\ud83d\udd34 Bear (ML: 3)", "PER": "N/A", "PBV": "N/A"}, {"Ticker": "EMTK", "Signal_Date": "2026-02-25", "Bars_Ago": 0, "Open": 935, "Close": 920, "Pct_Change_Price": -0.54, "Volume": 32681700, "Volume_Spike": false, "KO": -228119509.31, "UT_Buy": false, "ST_Trend": -1, "Aroon_Up": 50.0, "UT_Pos": -1, "PSAR_Trend": "Bull", "Kernel_Color": "\ud83d\udd34", "Kernel_Flip": "\u274c Tidak", "Pattern_Label": "\ud83d\udd34 Bear (ML: 2)", "PER": "N/A", "PBV": "N/A"}, {"Ticker": "MGRO", "Signal_Date": "2026-02-25", "Bars_Ago": 0, "Open": 705, "Close": 705, "Pct_Change_Price": -0.7, "Volume": 3696900, "Volume_Spike": false, "KO": 1682762.75, "UT_Buy": false, "ST_Trend": -1, "Aroon_Up": 37.5, "UT_Pos": -1, "PSAR_Trend": "Bull", "Kernel_Color": "\ud83d\udd34", "Kernel_Flip": "\u274c Tidak", "Pattern_Label": "\ud83d\udd34 Bear (ML: 3)", "PER": 31.24, "PBV": "N/A"}, {"Ticker": "WINE", "Signal_Date": "2026-02-25", "Bars_Ago": 0, "Open": 204, "Close": 204, "Pct_Change_Price": -0.97, "Volume": 2355100, "Volume_Spike": false, "KO": -3828393.32, "UT_Buy": false, "ST_Trend": -1, "Aroon_Up": 37.5, "UT_Pos": -1, "PSAR_Trend": "Bear", "Kernel_Color": "\ud83d\udd34", "Kernel_Flip": "\u274c Tidak", "Pattern_Label": "\ud83d\udd34 Bear (ML: 4)", "PER": "N/A", "PBV": "N/A"}, {"Ticker": "PTMP", "Signal_Date": "2026-02-25", "Bars_Ago": 0, "Open": 76, "Close": 75, "Pct_Change_Price": -1.32, "Volume": 8167200, "Volume_Spike": false, "KO": 100136354.34, "UT_Buy": false, "ST_Trend": -1, "Aroon_Up": 87.5, "UT_Pos": 1, "PSAR_Trend": "Bull", "Kernel_Color": "\ud83d\udd34", "Kernel_Flip": "\u274c Tidak", "Pattern_Label": "\ud83d\udd34 Bear (ML: -3)", "PER": "N/A", "PBV": "N/A"}, {"Ticker": "SOUL", "Signal_Date": "2026-02-25", "Bars_Ago": 0, "Open": 71, "Close": 71, "Pct_Change_Price": -1.39, "Volume": 1911000, "Volume_Spike": false, "KO": -4953531.2, "UT_Buy": false, "ST_Trend": -1, "Aroon_Up": 37.5, "UT_Pos": 1, "PSAR_Trend": "Bull", "Kernel_Color": "\ud83d\udd34", "Kernel_Flip": "\u274c Tidak", "Pattern_Label": "\ud83d\udd34 Bear (ML: 1)", "PER": 46.86, "PBV": -32.52}, {"Ticker": "PNLF", "Signal_Date": "2026-02-25", "Bars_Ago": 0, "Open": 278, "Close": 274, "Pct_Change_Price": -1.44, "Volume": 38503500, "Volume_Spike": false, "KO": -374904361.87, "UT_Buy": false, "ST_Trend": -1, "Aroon_Up": 50.0, "UT_Pos": -1, "PSAR_Trend": "Bull", "Kernel_Color": "\ud83d\udd34", "Kernel_Flip": "\u274c Tidak", "Pattern_Label": "\ud83d\udd34 Bear (ML: -1)", "PER": "N/A", "PBV": "N/A"}, {"Ticker": "CSRA", "Signal_Date": "2026-02-25", "Bars_Ago": 0, "Open": 1000, "Close": 985, "Pct_Change_Price": -1.5, "Volume": 597100, "Volume_Spike": false, "KO": 4903802.8, "UT_Buy": false, "ST_Trend": -1, "Aroon_Up": 62.5, "UT_Pos": -1, "PSAR_Trend": "Bear", "Kernel_Color": "\ud83d\udd34", "Kernel_Flip": "\u274c Tidak", "Pattern_Label": "\ud83d\udd34 Bear (ML: 0)", "PER": "N/A", "PBV": "N/A"}, {"Ticker": "BOAT", "Signal_Date": "2026-02-25", "Bars_Ago": 0, "Open": 177, "Close": 174, "Pct_Change_Price": -1.69, "Volume": 5029800, "Volume_Spike": false, "KO": -426286606.59, "UT_Buy": false, "ST_Trend": -1, "Aroon_Up": 50.0, "UT_Pos": 1, "PSAR_Trend": "Bull", "Kernel_Color": "\ud83d\udd34", "Kernel_Flip": "\u274c Tidak", "Pattern_Label": "\ud83d\udd34 Bear (ML: -4)", "PER": 9.31, "PBV": "N/A"}, {"Ticker": "CBRE", "Signal_Date": "2026-02-25", "Bars_Ago": 0, "Open": 860, "Close": 840, "Pct_Change_Price": -1.75, "Volume": 8869500, "Volume_Spike": false, "KO": -253249969.92, "UT_Buy": false, "ST_Trend": -1, "Aroon_Up": 75.0, "UT_Pos": 1, "PSAR_Trend": "Bull", "Kernel_Color": "\ud83d\udd34", "Kernel_Flip": "\u274c Tidak", "Pattern_Label": "\ud83d\udd34 Bear (ML: 0)", "PER": 33.69, "PBV": 5.09}, {"Ticker": "ADCP", "Signal_Date": "2026-02-25", "Bars_Ago": 0, "Open": 57, "Close": 56, "Pct_Change_Price": -1.75, "Volume": 5313300, "Volume_Spike": false, "KO": -348761702.83, "UT_Buy": false, "ST_Trend": -1, "Aroon_Up": 12.5, "UT_Pos": -1, "PSAR_Trend": "Bear", "Kernel_Color": "\ud83d\udd34", "Kernel_Flip": "\u274c Tidak", "Pattern_Label": "\ud83d\udd34 Bear (ML: 0)", "PER": "N/A", "PBV": "N/A"}, {"Ticker": "BBHI", "Signal_Date": "2026-02-25", "Bars_Ago": 0, "Open": 1445, "Close": 1395, "Pct_Change_Price": -1.76, "Volume": 828400, "Volume_Spike": false, "KO": -2883228.85, "UT_Buy": false, "ST_Trend": -1, "Aroon_Up": 0.0, "UT_Pos": -1, "PSAR_Trend": "Bull", "Kernel_Color": "\ud83d\udd34", "Kernel_Flip": "\u274c Tidak", "Pattern_Label": "\ud83d\udd34 Bear (ML: -4)", "PER": "N/A", "PBV": "N/A"}, {"Ticker": "PZZA", "Signal_Date": "2026-02-25", "Bars_Ago": 0, "Open": 218, "Close": 212, "Pct_Change_Price": -1.85, "Volume": 1437200, "Volume_Spike": false, "KO": 1776676.66, "UT_Buy": false, "ST_Trend": -1, "Aroon_Up": 50.0, "UT_Pos": -1, "PSAR_Trend": "Bull", "Kernel_Color": "\ud83d\udd34", "Kernel_Flip": "\u274c Tidak", "Pattern_Label": "\ud83d\udd34 Bear (ML: 1)", "PER": 41.04, "PBV": -2.72}, {"Ticker": "PANI", "Signal_Date": "2026-02-25", "Bars_Ago": 0, "Open": 10100, "Close": 9900, "Pct_Change_Price": -1.98, "Volume": 4699000, "Volume_Spike": false, "KO": 3623299.41, "UT_Buy": false, "ST_Trend": -1, "Aroon_Up": 0.0, "UT_Pos": -1, "PSAR_Trend": "Bull", "Kernel_Color": "\ud83d\udd34", "Kernel_Flip": "\u274c Tidak", "Pattern_Label": "\ud83d\udd34 Bear (ML: 1)", "PER": "N/A", "PBV": "N/A"}, {"Ticker": "OPMS", "Signal_Date": "2026-02-25", "Bars_Ago": 0, "Open": 146, "Close": 143, "Pct_Change_Price": -2.05, "Volume": 5641000, "Volume_Spike": false, "KO": -539722353.14, "UT_Buy": false, "ST_Trend": -1, "Aroon_Up": 62.5, "UT_Pos": -1, "PSAR_Trend": "Bull", "Kernel_Color": "\ud83d\udd34", "Kernel_Flip": "\u274c Tidak", "Pattern_Label": "\ud83d\udd34 Bear (ML: 2)", "PER": "N/A", "PBV": "N/A"}, {"Ticker": "JARR", "Signal_Date": "2026-02-25", "Bars_Ago": 0, "Open": 2570, "Close": 2500, "Pct_Change_Price": -2.34, "Volume": 2149100, "Volume_Spike": false, "KO": -107835482.92, "UT_Buy": false, "ST_Trend": -1, "Aroon_Up": 37.5, "UT_Pos": 1, "PSAR_Trend": "Bull", "Kernel_Color": "\ud83d\udd34", "Kernel_Flip": "\u274c Tidak", "Pattern_Label": "\ud83d\udd34 Bear (ML: -2)", "PER": "N/A", "PBV": "N/A"}, {"Ticker": "RUIS", "Signal_Date": "2026-02-25", "Bars_Ago": 0, "Open": 258, "Close": 250, "Pct_Change_Price": -2.34, "Volume": 2094500, "Volume_Spike": false, "KO": -53525360.37, "UT_Buy": false, "ST_Trend": -1, "Aroon_Up": 50.0, "UT_Pos": 1, "PSAR_Trend": "Bull", "Kernel_Color": "\ud83d\udd34", "Kernel_Flip": "\u274c Tidak", "Pattern_Label": "\ud83d\udd34 Bear (ML: 0)", "PER": "N/A", "PBV": "N/A"}, {"Ticker": "GDST", "Signal_Date": "2026-02-25", "Bars_Ago": 0, "Open": 118, "Close": 115, "Pct_Change_Price": -2.54, "Volume": 665000, "Volume_Spike": false, "KO": -18763309.18, "UT_Buy": false, "ST_Trend": -1, "Aroon_Up": 87.5, "UT_Pos": 1, "PSAR_Trend": "Bull", "Kernel_Color": "\ud83d\udd34", "Kernel_Flip": "\u274c Tidak", "Pattern_Label": "\ud83d\udd34 Bear (ML: -1)", "PER": "N/A", "PBV": -3.65}, {"Ticker": "GZCO", "Signal_Date": "2026-02-25", "Bars_Ago": 0, "Open": 222, "Close": 214, "Pct_Change_Price": -2.73, "Volume": 18601200, "Volume_Spike": false, "KO": -1187535971.79, "UT_Buy": false, "ST_Trend": -1, "Aroon_Up": 37.5, "UT_Pos": 1, "PSAR_Trend": "Bull", "Kernel_Color": "\ud83d\udd34", "Kernel_Flip": "\u274c Tidak", "Pattern_Label": "\ud83d\udd34 Bear (ML: -2)", "PER": "N/A", "PBV": "N/A"}, {"Ticker": "AEGS", "Signal_Date": "2026-02-25", "Bars_Ago": 0, "Open": 73, "Close": 70, "Pct_Change_Price": -2.78, "Volume": 6105700, "Volume_Spike": false, "KO": 85033038.91, "UT_Buy": false, "ST_Trend": -1, "Aroon_Up": 87.5, "UT_Pos": 1, "PSAR_Trend": "Bull", "Kernel_Color": "\ud83d\udd34", "Kernel_Flip": "\u274c Tidak", "Pattern_Label": "\ud83d\udd34 Bear (ML: 0)", "PER": "N/A", "PBV": "N/A"}, {"Ticker": "BNBA", "Signal_Date": "2026-02-25", "Bars_Ago": 0, "Open": 900, "Close": 865, "Pct_Change_Price": -3.35, "Volume": 806400, "Volume_Spike": false, "KO": -14668883.63, "UT_Buy": false, "ST_Trend": -1, "Aroon_Up": 87.5, "UT_Pos": -1, "PSAR_Trend": "Bear", "Kernel_Color": "\ud83d\udd34", "Kernel_Flip": "\u274c Tidak", "Pattern_Label": "\ud83d\udd34 Bear (ML: 0)", "PER": "N/A", "PBV": "N/A"}]}