{"last_update": "2025-12-15 17:00:00 WIB (Backfilled)", "super_screener": [{"Ticker": "PPRE", "Signal_Date": "2025-12-15", "Bars_Ago": 0, "Open": 118, "Close": 157, "Pct_Change_Price": 34.19, "Volume": 1257183400, "Volume_Spike": true, "KO": 2073587811.33, "UT_Buy": true, "ST_Trend": 1, "Aroon_Up": 100.0, "UT_Pos": 1, "PSAR_Trend": "Bull", "Pattern_Label": "POP_CEPAT"}, {"Ticker": "BEER", "Signal_Date": "2025-12-15", "Bars_Ago": 0, "Open": 220, "Close": 260, "Pct_Change_Price": 25.0, "Volume": 28847100, "Volume_Spike": true, "KO": 1430166.78, "UT_Buy": true, "ST_Trend": 1, "Aroon_Up": 100.0, "UT_Pos": 1, "PSAR_Trend": "Bull", "Pattern_Label": "POP_CEPAT"}, {"Ticker": "DART", "Signal_Date": "2025-12-15", "Bars_Ago": 0, "Open": 177, "Close": 214, "Pct_Change_Price": 20.9, "Volume": 20373400, "Volume_Spike": true, "KO": 33907077.96, "UT_Buy": true, "ST_Trend": 1, "Aroon_Up": 100.0, "UT_Pos": 1, "PSAR_Trend": "Bull", "Pattern_Label": "POP_CEPAT"}, {"Ticker": "DMND", "Signal_Date": "2025-12-15", "Bars_Ago": 0, "Open": 630, "Close": 735, "Pct_Change_Price": 17.6, "Volume": 2625400, "Volume_Spike": true, "KO": 5513544.31, "UT_Buy": true, "ST_Trend": 1, "Aroon_Up": 100.0, "UT_Pos": 1, "PSAR_Trend": "Bull", "Pattern_Label": "POP_CEPAT"}, {"Ticker": "WEGE", "Signal_Date": "2025-12-15", "Bars_Ago": 0, "Open": 65, "Close": 75, "Pct_Change_Price": 15.38, "Volume": 277506800, "Volume_Spike": true, "KO": -163604114.37, "UT_Buy": true, "ST_Trend": 1, "Aroon_Up": 100.0, "UT_Pos": 1, "PSAR_Trend": "Bull", "Pattern_Label": "POP_CEPAT"}, {"Ticker": "TUGU", "Signal_Date": "2025-12-15", "Bars_Ago": 0, "Open": 1095, "Close": 1165, "Pct_Change_Price": 7.87, "Volume": 22518600, "Volume_Spike": true, "KO": 43169302.26, "UT_Buy": true, "ST_Trend": 1, "Aroon_Up": 100.0, "UT_Pos": 1, "PSAR_Trend": "Bull", "Pattern_Label": "RUNNER"}, {"Ticker": "ESSA", "Signal_Date": "2025-12-15", "Bars_Ago": 0, "Open": 610, "Close": 655, "Pct_Change_Price": 7.38, "Volume": 104034300, "Volume_Spike": true, "KO": -58243525.59, "UT_Buy": true, "ST_Trend": 1, "Aroon_Up": 100.0, "UT_Pos": 1, "PSAR_Trend": "Bull", "Pattern_Label": "RUNNER"}, {"Ticker": "APLN", "Signal_Date": "2025-12-15", "Bars_Ago": 0, "Open": 103, "Close": 108, "Pct_Change_Price": 5.88, "Volume": 89615000, "Volume_Spike": true, "KO": 259282759.55, "UT_Buy": true, "ST_Trend": 1, "Aroon_Up": 100.0, "UT_Pos": 1, "PSAR_Trend": "Bull", "Pattern_Label": "RUNNER"}, {"Ticker": "BBHI", "Signal_Date": "2025-12-15", "Bars_Ago": 0, "Open": 1485, "Close": 1535, "Pct_Change_Price": 3.72, "Volume": 5545900, "Volume_Spike": true, "KO": 8007504.95, "UT_Buy": true, "ST_Trend": 1, "Aroon_Up": 100.0, "UT_Pos": 1, "PSAR_Trend": "Bull", "Pattern_Label": "RUNNER"}, {"Ticker": "KPIG", "Signal_Date": "2025-12-15", "Bars_Ago": 0, "Open": 135, "Close": 137, "Pct_Change_Price": 2.24, "Volume": 164410300, "Volume_Spike": true, "KO": -496633493.55, "UT_Buy": false, "ST_Trend": -1, "Aroon_Up": 100.0, "UT_Pos": 1, "PSAR_Trend": "Bull", "Pattern_Label": "NOISE_TRAP"}, {"Ticker": "HRTA", "Signal_Date": "2025-12-12", "Bars_Ago": 1, "Open": 1495, "Close": 1800, "Pct_Change_Price": 23.71, "Volume": 180861100, "Volume_Spike": true, "KO": 24799786.39, "UT_Buy": true, "ST_Trend": 1, "Aroon_Up": 100.0, "UT_Pos": 1, "PSAR_Trend": "Bull", "Pattern_Label": "POP_CEPAT"}, {"Ticker": "PSAB", "Signal_Date": "2025-12-12", "Bars_Ago": 1, "Open": 555, "Close": 605, "Pct_Change_Price": 11.01, "Volume": 610171200, "Volume_Spike": true, "KO": -103227272.74, "UT_Buy": false, "ST_Trend": 1, "Aroon_Up": 100.0, "UT_Pos": 1, "PSAR_Trend": "Bull", "Pattern_Label": "RUNNER"}, {"Ticker": "ARKO", "Signal_Date": "2025-12-12", "Bars_Ago": 1, "Open": 5150, "Close": 5150, "Pct_Change_Price": 9.57, "Volume": 21273400, "Volume_Spike": true, "KO": 54006514.18, "UT_Buy": false, "ST_Trend": 1, "Aroon_Up": 100.0, "UT_Pos": 1, "PSAR_Trend": "Bull", "Pattern_Label": "RUNNER"}, {"Ticker": "AMMN", "Signal_Date": "2025-12-12", "Bars_Ago": 1, "Open": 6350, "Close": 6725, "Pct_Change_Price": 5.91, "Volume": 59828400, "Volume_Spike": true, "KO": 184054771.5, "UT_Buy": true, "ST_Trend": -1, "Aroon_Up": 100.0, "UT_Pos": 1, "PSAR_Trend": "Bull", "Pattern_Label": "POP_CEPAT"}, {"Ticker": "MSIN", "Signal_Date": "2025-12-12", "Bars_Ago": 1, "Open": 410, "Close": 434, "Pct_Change_Price": 5.85, "Volume": 147811500, "Volume_Spike": true, "KO": -425283548.3, "UT_Buy": true, "ST_Trend": -1, "Aroon_Up": 100.0, "UT_Pos": 1, "PSAR_Trend": "Bear", "Pattern_Label": "POP_CEPAT"}, {"Ticker": "ANTM", "Signal_Date": "2025-12-12", "Bars_Ago": 1, "Open": 2910, "Close": 3050, "Pct_Change_Price": 5.54, "Volume": 304157500, "Volume_Spike": true, "KO": -40142072.27, "UT_Buy": true, "ST_Trend": -1, "Aroon_Up": 100.0, "UT_Pos": 1, "PSAR_Trend": "Bull", "Pattern_Label": "POP_CEPAT"}], "aroon_ut": [{"Ticker": "PPRE", "Signal_Date": "2025-12-15", "Bars_Ago": 0, "Open": 118, "Close": 157, "Pct_Change_Price": 34.19, "Volume": 1257183400, "Volume_Spike": true, "KO": 2073587811.33, "UT_Buy": true, "ST_Trend": 1, "Aroon_Up": 100.0, "UT_Pos": 1, "PSAR_Trend": "Bull", "Pattern_Label": "POP_CEPAT"}, {"Ticker": "BEER", "Signal_Date": "2025-12-15", "Bars_Ago": 0, "Open": 220, "Close": 260, "Pct_Change_Price": 25.0, "Volume": 28847100, "Volume_Spike": true, "KO": 1430166.78, "UT_Buy": true, "ST_Trend": 1, "Aroon_Up": 100.0, "UT_Pos": 1, "PSAR_Trend": "Bull", "Pattern_Label": "POP_CEPAT"}, {"Ticker": "GMTD", "Signal_Date": "2025-12-15", "Bars_Ago": 0, "Open": 2140, "Close": 2630, "Pct_Change_Price": 22.9, "Volume": 47200, "Volume_Spike": true, "KO": -36565.67, "UT_Buy": true, "ST_Trend": 1, "Aroon_Up": 100.0, "UT_Pos": 1, "PSAR_Trend": "Bear", "Pattern_Label": "POP_CEPAT"}, {"Ticker": "DART", "Signal_Date": "2025-12-15", "Bars_Ago": 0, "Open": 177, "Close": 214, "Pct_Change_Price": 20.9, "Volume": 20373400, "Volume_Spike": true, "KO": 33907077.96, "UT_Buy": true, "ST_Trend": 1, "Aroon_Up": 100.0, "UT_Pos": 1, "PSAR_Trend": "Bull", "Pattern_Label": "POP_CEPAT"}, {"Ticker": "DMND", "Signal_Date": "2025-12-15", "Bars_Ago": 0, "Open": 630, "Close": 735, "Pct_Change_Price": 17.6, "Volume": 2625400, "Volume_Spike": true, "KO": 5513544.31, "UT_Buy": true, "ST_Trend": 1, "Aroon_Up": 100.0, "UT_Pos": 1, "PSAR_Trend": "Bull", "Pattern_Label": "POP_CEPAT"}, {"Ticker": "WEGE", "Signal_Date": "2025-12-15", "Bars_Ago": 0, "Open": 65, "Close": 75, "Pct_Change_Price": 15.38, "Volume": 277506800, "Volume_Spike": true, "KO": -163604114.37, "UT_Buy": true, "ST_Trend": 1, "Aroon_Up": 100.0, "UT_Pos": 1, "PSAR_Trend": "Bull", "Pattern_Label": "POP_CEPAT"}, {"Ticker": "HDFA", "Signal_Date": "2025-12-15", "Bars_Ago": 0, "Open": 140, "Close": 158, "Pct_Change_Price": 11.27, "Volume": 9492600, "Volume_Spike": true, "KO": -5919652.51, "UT_Buy": true, "ST_Trend": 1, "Aroon_Up": 100.0, "UT_Pos": 1, "PSAR_Trend": "Bear", "Pattern_Label": "RUNNER"}, {"Ticker": "ARTO", "Signal_Date": "2025-12-15", "Bars_Ago": 0, "Open": 2000, "Close": 2220, "Pct_Change_Price": 11.0, "Volume": 54620100, "Volume_Spike": true, "KO": 134649189.74, "UT_Buy": true, "ST_Trend": 1, "Aroon_Up": 100.0, "UT_Pos": 1, "PSAR_Trend": "Bull", "Pattern_Label": "RUNNER"}, {"Ticker": "TUGU", "Signal_Date": "2025-12-15", "Bars_Ago": 0, "Open": 1095, "Close": 1165, "Pct_Change_Price": 7.87, "Volume": 22518600, "Volume_Spike": true, "KO": 43169302.26, "UT_Buy": true, "ST_Trend": 1, "Aroon_Up": 100.0, "UT_Pos": 1, "PSAR_Trend": "Bull", "Pattern_Label": "RUNNER"}, {"Ticker": "ESSA", "Signal_Date": "2025-12-15", "Bars_Ago": 0, "Open": 610, "Close": 655, "Pct_Change_Price": 7.38, "Volume": 104034300, "Volume_Spike": true, "KO": -58243525.59, "UT_Buy": true, "ST_Trend": 1, "Aroon_Up": 100.0, "UT_Pos": 1, "PSAR_Trend": "Bull", "Pattern_Label": "RUNNER"}, {"Ticker": "APLN", "Signal_Date": "2025-12-15", "Bars_Ago": 0, "Open": 103, "Close": 108, "Pct_Change_Price": 5.88, "Volume": 89615000, "Volume_Spike": true, "KO": 259282759.55, "UT_Buy": true, "ST_Trend": 1, "Aroon_Up": 100.0, "UT_Pos": 1, "PSAR_Trend": "Bull", "Pattern_Label": "RUNNER"}, {"Ticker": "TOWR", "Signal_Date": "2025-12-15", "Bars_Ago": 0, "Open": 540, "Close": 570, "Pct_Change_Price": 5.56, "Volume": 39206100, "Volume_Spike": true, "KO": -98653009.16, "UT_Buy": true, "ST_Trend": -1, "Aroon_Up": 100.0, "UT_Pos": 1, "PSAR_Trend": "Bull", "Pattern_Label": "POP_CEPAT"}, {"Ticker": "BBNI", "Signal_Date": "2025-12-15", "Bars_Ago": 0, "Open": 4270, "Close": 4440, "Pct_Change_Price": 4.72, "Volume": 57531500, "Volume_Spike": true, "KO": -90233686.62, "UT_Buy": true, "ST_Trend": 1, "Aroon_Up": 100.0, "UT_Pos": 1, "PSAR_Trend": "Bull", "Pattern_Label": "RUNNER"}, {"Ticker": "MDKA", "Signal_Date": "2025-12-15", "Bars_Ago": 0, "Open": 2280, "Close": 2350, "Pct_Change_Price": 4.44, "Volume": 153363100, "Volume_Spike": true, "KO": 270550093.36, "UT_Buy": true, "ST_Trend": -1, "Aroon_Up": 100.0, "UT_Pos": 1, "PSAR_Trend": "Bull", "Pattern_Label": "NOISE_TRAP"}, {"Ticker": "SIDO", "Signal_Date": "2025-12-15", "Bars_Ago": 0, "Open": 535, "Close": 550, "Pct_Change_Price": 3.77, "Volume": 40698400, "Volume_Spike": true, "KO": -24024152.87, "UT_Buy": true, "ST_Trend": -1, "Aroon_Up": 100.0, "UT_Pos": 1, "PSAR_Trend": "Bull", "Pattern_Label": "NOISE_TRAP"}, {"Ticker": "BBHI", "Signal_Date": "2025-12-15", "Bars_Ago": 0, "Open": 1485, "Close": 1535, "Pct_Change_Price": 3.72, "Volume": 5545900, "Volume_Spike": true, "KO": 8007504.95, "UT_Buy": true, "ST_Trend": 1, "Aroon_Up": 100.0, "UT_Pos": 1, "PSAR_Trend": "Bull", "Pattern_Label": "RUNNER"}, {"Ticker": "INDR", "Signal_Date": "2025-12-15", "Bars_Ago": 0, "Open": 2740, "Close": 2830, "Pct_Change_Price": 3.28, "Volume": 110700, "Volume_Spike": true, "KO": 171236.5, "UT_Buy": true, "ST_Trend": -1, "Aroon_Up": 100.0, "UT_Pos": 1, "PSAR_Trend": "Bull", "Pattern_Label": "NOISE_TRAP"}, {"Ticker": "VERN", "Signal_Date": "2025-12-15", "Bars_Ago": 0, "Open": 124, "Close": 132, "Pct_Change_Price": 7.32, "Volume": 11404700, "Volume_Spike": false, "KO": 20000164.24, "UT_Buy": true, "ST_Trend": 1, "Aroon_Up": 100.0, "UT_Pos": 1, "PSAR_Trend": "Bear", "Pattern_Label": "UNCLASSIFIED"}, {"Ticker": "KLBF", "Signal_Date": "2025-12-15", "Bars_Ago": 0, "Open": 1175, "Close": 1220, "Pct_Change_Price": 5.17, "Volume": 143415000, "Volume_Spike": false, "KO": -613259948.96, "UT_Buy": true, "ST_Trend": -1, "Aroon_Up": 100.0, "UT_Pos": 1, "PSAR_Trend": "Bull", "Pattern_Label": "NOISE_TRAP"}, {"Ticker": "BBRI", "Signal_Date": "2025-12-15", "Bars_Ago": 0, "Open": 3650, "Close": 3780, "Pct_Change_Price": 4.13, "Volume": 312694100, "Volume_Spike": false, "KO": -381546758.95, "UT_Buy": true, "ST_Trend": -1, "Aroon_Up": 100.0, "UT_Pos": 1, "PSAR_Trend": "Bull", "Pattern_Label": "NOISE_TRAP"}, {"Ticker": "BANK", "Signal_Date": "2025-12-15", "Bars_Ago": 0, "Open": 925, "Close": 960, "Pct_Change_Price": 3.78, "Volume": 10125500, "Volume_Spike": false, "KO": 117710422.27, "UT_Buy": true, "ST_Trend": 1, "Aroon_Up": 100.0, "UT_Pos": 1, "PSAR_Trend": "Bull", "Pattern_Label": "UNCLASSIFIED"}, {"Ticker": "ICBP", "Signal_Date": "2025-12-15", "Bars_Ago": 0, "Open": 8225, "Close": 8300, "Pct_Change_Price": 2.79, "Volume": 15671200, "Volume_Spike": false, "KO": -20818813.31, "UT_Buy": true, "ST_Trend": -1, "Aroon_Up": 100.0, "UT_Pos": 1, "PSAR_Trend": "Bear", "Pattern_Label": "NOISE_TRAP"}, {"Ticker": "BRMS", "Signal_Date": "2025-12-12", "Bars_Ago": 1, "Open": 1015, "Close": 1230, "Pct_Change_Price": 24.87, "Volume": 2563550200, "Volume_Spike": true, "KO": 4111186718.82, "UT_Buy": true, "ST_Trend": 1, "Aroon_Up": 100.0, "UT_Pos": 1, "PSAR_Trend": "Bull", "Pattern_Label": "POP_CEPAT"}, {"Ticker": "HRTA", "Signal_Date": "2025-12-12", "Bars_Ago": 1, "Open": 1495, "Close": 1800, "Pct_Change_Price": 23.71, "Volume": 180861100, "Volume_Spike": true, "KO": 24799786.39, "UT_Buy": true, "ST_Trend": 1, "Aroon_Up": 100.0, "UT_Pos": 1, "PSAR_Trend": "Bull", "Pattern_Label": "POP_CEPAT"}, {"Ticker": "AMMN", "Signal_Date": "2025-12-12", "Bars_Ago": 1, "Open": 6350, "Close": 6725, "Pct_Change_Price": 5.91, "Volume": 59828400, "Volume_Spike": true, "KO": 184054771.5, "UT_Buy": true, "ST_Trend": -1, "Aroon_Up": 100.0, "UT_Pos": 1, "PSAR_Trend": "Bull", "Pattern_Label": "POP_CEPAT"}, {"Ticker": "MSIN", "Signal_Date": "2025-12-12", "Bars_Ago": 1, "Open": 410, "Close": 434, "Pct_Change_Price": 5.85, "Volume": 147811500, "Volume_Spike": true, "KO": -425283548.3, "UT_Buy": true, "ST_Trend": -1, "Aroon_Up": 100.0, "UT_Pos": 1, "PSAR_Trend": "Bear", "Pattern_Label": "POP_CEPAT"}, {"Ticker": "ANTM", "Signal_Date": "2025-12-12", "Bars_Ago": 1, "Open": 2910, "Close": 3050, "Pct_Change_Price": 5.54, "Volume": 304157500, "Volume_Spike": true, "KO": -40142072.27, "UT_Buy": true, "ST_Trend": -1, "Aroon_Up": 100.0, "UT_Pos": 1, "PSAR_Trend": "Bull", "Pattern_Label": "POP_CEPAT"}, {"Ticker": "ARTA", "Signal_Date": "2025-12-12", "Bars_Ago": 1, "Open": 2910, "Close": 3000, "Pct_Change_Price": 4.53, "Volume": 14100, "Volume_Spike": true, "KO": -38347.8, "UT_Buy": true, "ST_Trend": 1, "Aroon_Up": 100.0, "UT_Pos": 1, "PSAR_Trend": "Bear", "Pattern_Label": "RUNNER"}], "ko_ut_vol": [{"Ticker": "PPRE", "Signal_Date": "2025-12-15", "Bars_Ago": 0, "Open": 118, "Close": 157, "Pct_Change_Price": 34.19, "Volume": 1257183400, "Volume_Spike": true, "KO": 2073587811.33, "UT_Buy": true, "ST_Trend": 1, "Aroon_Up": 100.0, "UT_Pos": 1, "PSAR_Trend": "Bull", "Pattern_Label": "POP_CEPAT"}, {"Ticker": "BEER", "Signal_Date": "2025-12-15", "Bars_Ago": 0, "Open": 220, "Close": 260, "Pct_Change_Price": 25.0, "Volume": 28847100, "Volume_Spike": true, "KO": 1430166.78, "UT_Buy": true, "ST_Trend": 1, "Aroon_Up": 100.0, "UT_Pos": 1, "PSAR_Trend": "Bull", "Pattern_Label": "POP_CEPAT"}, {"Ticker": "KOKA", "Signal_Date": "2025-12-15", "Bars_Ago": 0, "Open": 214, "Close": 252, "Pct_Change_Price": 24.75, "Volume": 119575700, "Volume_Spike": true, "KO": -336200454.03, "UT_Buy": true, "ST_Trend": -1, "Aroon_Up": 25.0, "UT_Pos": 1, "PSAR_Trend": "Bull", "Pattern_Label": "POP_CEPAT"}, {"Ticker": "DART", "Signal_Date": "2025-12-15", "Bars_Ago": 0, "Open": 177, "Close": 214, "Pct_Change_Price": 20.9, "Volume": 20373400, "Volume_Spike": true, "KO": 33907077.96, "UT_Buy": true, "ST_Trend": 1, "Aroon_Up": 100.0, "UT_Pos": 1, "PSAR_Trend": "Bull", "Pattern_Label": "POP_CEPAT"}, {"Ticker": "DMND", "Signal_Date": "2025-12-15", "Bars_Ago": 0, "Open": 630, "Close": 735, "Pct_Change_Price": 17.6, "Volume": 2625400, "Volume_Spike": true, "KO": 5513544.31, "UT_Buy": true, "ST_Trend": 1, "Aroon_Up": 100.0, "UT_Pos": 1, "PSAR_Trend": "Bull", "Pattern_Label": "POP_CEPAT"}, {"Ticker": "LAPD", "Signal_Date": "2025-12-15", "Bars_Ago": 0, "Open": 163, "Close": 184, "Pct_Change_Price": 15.72, "Volume": 217974000, "Volume_Spike": true, "KO": 54908014.29, "UT_Buy": true, "ST_Trend": -1, "Aroon_Up": 25.0, "UT_Pos": 1, "PSAR_Trend": "Bear", "Pattern_Label": "POP_CEPAT"}, {"Ticker": "WEGE", "Signal_Date": "2025-12-15", "Bars_Ago": 0, "Open": 65, "Close": 75, "Pct_Change_Price": 15.38, "Volume": 277506800, "Volume_Spike": true, "KO": -163604114.37, "UT_Buy": true, "ST_Trend": 1, "Aroon_Up": 100.0, "UT_Pos": 1, "PSAR_Trend": "Bull", "Pattern_Label": "POP_CEPAT"}, {"Ticker": "HDFA", "Signal_Date": "2025-12-15", "Bars_Ago": 0, "Open": 140, "Close": 158, "Pct_Change_Price": 11.27, "Volume": 9492600, "Volume_Spike": true, "KO": -5919652.51, "UT_Buy": true, "ST_Trend": 1, "Aroon_Up": 100.0, "UT_Pos": 1, "PSAR_Trend": "Bear", "Pattern_Label": "RUNNER"}, {"Ticker": "KKGI", "Signal_Date": "2025-12-15", "Bars_Ago": 0, "Open": 326, "Close": 354, "Pct_Change_Price": 9.26, "Volume": 57767500, "Volume_Spike": true, "KO": 97010042.9, "UT_Buy": true, "ST_Trend": 1, "Aroon_Up": 100.0, "UT_Pos": 1, "PSAR_Trend": "Bull", "Pattern_Label": "RUNNER"}, {"Ticker": "BLTA", "Signal_Date": "2025-12-15", "Bars_Ago": 0, "Open": 40, "Close": 40, "Pct_Change_Price": 8.11, "Volume": 13172600, "Volume_Spike": true, "KO": 12458476.13, "UT_Buy": true, "ST_Trend": -1, "Aroon_Up": 37.5, "UT_Pos": 1, "PSAR_Trend": "Bull", "Pattern_Label": "POP_CEPAT"}, {"Ticker": "TUGU", "Signal_Date": "2025-12-15", "Bars_Ago": 0, "Open": 1095, "Close": 1165, "Pct_Change_Price": 7.87, "Volume": 22518600, "Volume_Spike": true, "KO": 43169302.26, "UT_Buy": true, "ST_Trend": 1, "Aroon_Up": 100.0, "UT_Pos": 1, "PSAR_Trend": "Bull", "Pattern_Label": "RUNNER"}, {"Ticker": "AGRO", "Signal_Date": "2025-12-15", "Bars_Ago": 0, "Open": 234, "Close": 248, "Pct_Change_Price": 7.83, "Volume": 159045500, "Volume_Spike": true, "KO": 337214739.17, "UT_Buy": true, "ST_Trend": 1, "Aroon_Up": 100.0, "UT_Pos": 1, "PSAR_Trend": "Bear", "Pattern_Label": "RUNNER"}, {"Ticker": "ESSA", "Signal_Date": "2025-12-15", "Bars_Ago": 0, "Open": 610, "Close": 655, "Pct_Change_Price": 7.38, "Volume": 104034300, "Volume_Spike": true, "KO": -58243525.59, "UT_Buy": true, "ST_Trend": 1, "Aroon_Up": 100.0, "UT_Pos": 1, "PSAR_Trend": "Bull", "Pattern_Label": "RUNNER"}, {"Ticker": "BBTN", "Signal_Date": "2025-12-15", "Bars_Ago": 0, "Open": 1100, "Close": 1170, "Pct_Change_Price": 7.34, "Volume": 71873200, "Volume_Spike": true, "KO": -231472681.09, "UT_Buy": true, "ST_Trend": 1, "Aroon_Up": 0.0, "UT_Pos": 1, "PSAR_Trend": "Bull", "Pattern_Label": "RUNNER"}, {"Ticker": "MTLA", "Signal_Date": "2025-12-15", "Bars_Ago": 0, "Open": 416, "Close": 446, "Pct_Change_Price": 6.19, "Volume": 770400, "Volume_Spike": true, "KO": -137330.0, "UT_Buy": true, "ST_Trend": -1, "Aroon_Up": 100.0, "UT_Pos": 1, "PSAR_Trend": "Bull", "Pattern_Label": "POP_CEPAT"}, {"Ticker": "BRIS", "Signal_Date": "2025-12-15", "Bars_Ago": 0, "Open": 2170, "Close": 2290, "Pct_Change_Price": 6.02, "Volume": 44711900, "Volume_Spike": true, "KO": -42169757.36, "UT_Buy": true, "ST_Trend": -1, "Aroon_Up": 0.0, "UT_Pos": 1, "PSAR_Trend": "Bull", "Pattern_Label": "POP_CEPAT"}, {"Ticker": "APLN", "Signal_Date": "2025-12-15", "Bars_Ago": 0, "Open": 103, "Close": 108, "Pct_Change_Price": 5.88, "Volume": 89615000, "Volume_Spike": true, "KO": 259282759.55, "UT_Buy": true, "ST_Trend": 1, "Aroon_Up": 100.0, "UT_Pos": 1, "PSAR_Trend": "Bull", "Pattern_Label": "RUNNER"}, {"Ticker": "BNII", "Signal_Date": "2025-12-15", "Bars_Ago": 0, "Open": 212, "Close": 218, "Pct_Change_Price": 5.83, "Volume": 16675200, "Volume_Spike": true, "KO": 29997097.92, "UT_Buy": true, "ST_Trend": 1, "Aroon_Up": 100.0, "UT_Pos": 1, "PSAR_Trend": "Bull", "Pattern_Label": "RUNNER"}, {"Ticker": "NIKL", "Signal_Date": "2025-12-15", "Bars_Ago": 0, "Open": 390, "Close": 404, "Pct_Change_Price": 5.21, "Volume": 23604600, "Volume_Spike": true, "KO": -20326936.3, "UT_Buy": true, "ST_Trend": -1, "Aroon_Up": 100.0, "UT_Pos": 1, "PSAR_Trend": "Bull", "Pattern_Label": "POP_CEPAT"}, {"Ticker": "BBNI", "Signal_Date": "2025-12-15", "Bars_Ago": 0, "Open": 4270, "Close": 4440, "Pct_Change_Price": 4.72, "Volume": 57531500, "Volume_Spike": true, "KO": -90233686.62, "UT_Buy": true, "ST_Trend": 1, "Aroon_Up": 100.0, "UT_Pos": 1, "PSAR_Trend": "Bull", "Pattern_Label": "RUNNER"}, {"Ticker": "SMRA", "Signal_Date": "2025-12-15", "Bars_Ago": 0, "Open": 370, "Close": 384, "Pct_Change_Price": 3.78, "Volume": 55170500, "Volume_Spike": true, "KO": -152622316.42, "UT_Buy": true, "ST_Trend": -1, "Aroon_Up": 0.0, "UT_Pos": 1, "PSAR_Trend": "Bull", "Pattern_Label": "NOISE_TRAP"}, {"Ticker": "SIDO", "Signal_Date": "2025-12-15", "Bars_Ago": 0, "Open": 535, "Close": 550, "Pct_Change_Price": 3.77, "Volume": 40698400, "Volume_Spike": true, "KO": -24024152.87, "UT_Buy": true, "ST_Trend": -1, "Aroon_Up": 100.0, "UT_Pos": 1, "PSAR_Trend": "Bull", "Pattern_Label": "NOISE_TRAP"}, {"Ticker": "BBHI", "Signal_Date": "2025-12-15", "Bars_Ago": 0, "Open": 1485, "Close": 1535, "Pct_Change_Price": 3.72, "Volume": 5545900, "Volume_Spike": true, "KO": 8007504.95, "UT_Buy": true, "ST_Trend": 1, "Aroon_Up": 100.0, "UT_Pos": 1, "PSAR_Trend": "Bull", "Pattern_Label": "RUNNER"}, {"Ticker": "IRRA", "Signal_Date": "2025-12-15", "Bars_Ago": 0, "Open": 442, "Close": 456, "Pct_Change_Price": 3.64, "Volume": 3145500, "Volume_Spike": true, "KO": 2667777.81, "UT_Buy": true, "ST_Trend": 1, "Aroon_Up": 50.0, "UT_Pos": 1, "PSAR_Trend": "Bull", "Pattern_Label": "RUNNER"}, {"Ticker": "BUKA", "Signal_Date": "2025-12-15", "Bars_Ago": 0, "Open": 164, "Close": 168, "Pct_Change_Price": 3.07, "Volume": 315685000, "Volume_Spike": true, "KO": -735041584.46, "UT_Buy": true, "ST_Trend": 1, "Aroon_Up": 75.0, "UT_Pos": 1, "PSAR_Trend": "Bear", "Pattern_Label": "RUNNER"}, {"Ticker": "ASRI", "Signal_Date": "2025-12-15", "Bars_Ago": 0, "Open": 165, "Close": 169, "Pct_Change_Price": 3.05, "Volume": 66932300, "Volume_Spike": true, "KO": -127483462.72, "UT_Buy": true, "ST_Trend": 1, "Aroon_Up": 0.0, "UT_Pos": 1, "PSAR_Trend": "Bear", "Pattern_Label": "RUNNER"}, {"Ticker": "BBRI", "Signal_Date": "2025-12-15", "Bars_Ago": 0, "Open": 3650, "Close": 3780, "Pct_Change_Price": 4.13, "Volume": 312694100, "Volume_Spike": false, "KO": -381546758.95, "UT_Buy": true, "ST_Trend": -1, "Aroon_Up": 100.0, "UT_Pos": 1, "PSAR_Trend": "Bull", "Pattern_Label": "NOISE_TRAP"}, {"Ticker": "SBMA", "Signal_Date": "2025-12-15", "Bars_Ago": 0, "Open": 128, "Close": 132, "Pct_Change_Price": 3.12, "Volume": 2083300, "Volume_Spike": false, "KO": -2123177.58, "UT_Buy": true, "ST_Trend": 1, "Aroon_Up": 25.0, "UT_Pos": 1, "PSAR_Trend": "Bear", "Pattern_Label": "UNCLASSIFIED"}, {"Ticker": "YOII", "Signal_Date": "2025-12-15", "Bars_Ago": 0, "Open": 97, "Close": 98, "Pct_Change_Price": 2.08, "Volume": 5500000, "Volume_Spike": false, "KO": -40067483.95, "UT_Buy": true, "ST_Trend": 1, "Aroon_Up": 0.0, "UT_Pos": 1, "PSAR_Trend": "Bear", "Pattern_Label": "UNCLASSIFIED"}, {"Ticker": "MSTI", "Signal_Date": "2025-12-15", "Bars_Ago": 0, "Open": 1380, "Close": 1400, "Pct_Change_Price": 1.82, "Volume": 1744000, "Volume_Spike": false, "KO": -3250381.53, "UT_Buy": true, "ST_Trend": -1, "Aroon_Up": 0.0, "UT_Pos": 1, "PSAR_Trend": "Bear", "Pattern_Label": "NOISE_TRAP"}, {"Ticker": "HRTA", "Signal_Date": "2025-12-12", "Bars_Ago": 1, "Open": 1495, "Close": 1800, "Pct_Change_Price": 23.71, "Volume": 180861100, "Volume_Spike": true, "KO": 24799786.39, "UT_Buy": true, "ST_Trend": 1, "Aroon_Up": 100.0, "UT_Pos": 1, "PSAR_Trend": "Bull", "Pattern_Label": "POP_CEPAT"}, {"Ticker": "TINS", "Signal_Date": "2025-12-12", "Bars_Ago": 1, "Open": 3130, "Close": 3400, "Pct_Change_Price": 11.11, "Volume": 156891200, "Volume_Spike": true, "KO": -506593778.13, "UT_Buy": true, "ST_Trend": 1, "Aroon_Up": 25.0, "UT_Pos": 1, "PSAR_Trend": "Bear", "Pattern_Label": "RUNNER"}, {"Ticker": "AGRS", "Signal_Date": "2025-12-12", "Bars_Ago": 1, "Open": 81, "Close": 84, "Pct_Change_Price": 9.09, "Volume": 261822100, "Volume_Spike": true, "KO": 730068853.81, "UT_Buy": true, "ST_Trend": 1, "Aroon_Up": 100.0, "UT_Pos": 1, "PSAR_Trend": "Bull", "Pattern_Label": "RUNNER"}, {"Ticker": "AMMN", "Signal_Date": "2025-12-12", "Bars_Ago": 1, "Open": 6350, "Close": 6725, "Pct_Change_Price": 5.91, "Volume": 59828400, "Volume_Spike": true, "KO": 184054771.5, "UT_Buy": true, "ST_Trend": -1, "Aroon_Up": 100.0, "UT_Pos": 1, "PSAR_Trend": "Bull", "Pattern_Label": "POP_CEPAT"}, {"Ticker": "MSIN", "Signal_Date": "2025-12-12", "Bars_Ago": 1, "Open": 410, "Close": 434, "Pct_Change_Price": 5.85, "Volume": 147811500, "Volume_Spike": true, "KO": -425283548.3, "UT_Buy": true, "ST_Trend": -1, "Aroon_Up": 100.0, "UT_Pos": 1, "PSAR_Trend": "Bear", "Pattern_Label": "POP_CEPAT"}, {"Ticker": "ANTM", "Signal_Date": "2025-12-12", "Bars_Ago": 1, "Open": 2910, "Close": 3050, "Pct_Change_Price": 5.54, "Volume": 304157500, "Volume_Spike": true, "KO": -40142072.27, "UT_Buy": true, "ST_Trend": -1, "Aroon_Up": 100.0, "UT_Pos": 1, "PSAR_Trend": "Bull", "Pattern_Label": "POP_CEPAT"}, {"Ticker": "TSPC", "Signal_Date": "2025-12-12", "Bars_Ago": 1, "Open": 2690, "Close": 2770, "Pct_Change_Price": 3.75, "Volume": 3218400, "Volume_Spike": true, "KO": -2246217.42, "UT_Buy": true, "ST_Trend": -1, "Aroon_Up": 50.0, "UT_Pos": 1, "PSAR_Trend": "Bull", "Pattern_Label": "NOISE_TRAP"}], "aroon_psar": [{"Ticker": "PPRE", "Signal_Date": "2025-12-15", "Bars_Ago": 0, "Open": 118, "Close": 157, "Pct_Change_Price": 34.19, "Volume": 1257183400, "Volume_Spike": true, "KO": 2073587811.33, "UT_Buy": true, "ST_Trend": 1, "Aroon_Up": 100.0, "UT_Pos": 1, "PSAR_Trend": "Bull", "Pattern_Label": "POP_CEPAT"}, {"Ticker": "BEER", "Signal_Date": "2025-12-15", "Bars_Ago": 0, "Open": 220, "Close": 260, "Pct_Change_Price": 25.0, "Volume": 28847100, "Volume_Spike": true, "KO": 1430166.78, "UT_Buy": true, "ST_Trend": 1, "Aroon_Up": 100.0, "UT_Pos": 1, "PSAR_Trend": "Bull", "Pattern_Label": "POP_CEPAT"}, {"Ticker": "IATA", "Signal_Date": "2025-12-15", "Bars_Ago": 0, "Open": 113, "Close": 138, "Pct_Change_Price": 24.32, "Volume": 702000800, "Volume_Spike": true, "KO": 2255307352.2, "UT_Buy": false, "ST_Trend": 1, "Aroon_Up": 100.0, "UT_Pos": 1, "PSAR_Trend": "Bull", "Pattern_Label": "POP_CEPAT"}, {"Ticker": "DART", "Signal_Date": "2025-12-15", "Bars_Ago": 0, "Open": 177, "Close": 214, "Pct_Change_Price": 20.9, "Volume": 20373400, "Volume_Spike": true, "KO": 33907077.96, "UT_Buy": true, "ST_Trend": 1, "Aroon_Up": 100.0, "UT_Pos": 1, "PSAR_Trend": "Bull", "Pattern_Label": "POP_CEPAT"}, {"Ticker": "DMND", "Signal_Date": "2025-12-15", "Bars_Ago": 0, "Open": 630, "Close": 735, "Pct_Change_Price": 17.6, "Volume": 2625400, "Volume_Spike": true, "KO": 5513544.31, "UT_Buy": true, "ST_Trend": 1, "Aroon_Up": 100.0, "UT_Pos": 1, "PSAR_Trend": "Bull", "Pattern_Label": "POP_CEPAT"}, {"Ticker": "WEGE", "Signal_Date": "2025-12-15", "Bars_Ago": 0, "Open": 65, "Close": 75, "Pct_Change_Price": 15.38, "Volume": 277506800, "Volume_Spike": true, "KO": -163604114.37, "UT_Buy": true, "ST_Trend": 1, "Aroon_Up": 100.0, "UT_Pos": 1, "PSAR_Trend": "Bull", "Pattern_Label": "POP_CEPAT"}, {"Ticker": "INDY", "Signal_Date": "2025-12-15", "Bars_Ago": 0, "Open": 2020, "Close": 2250, "Pct_Change_Price": 13.35, "Volume": 224794700, "Volume_Spike": true, "KO": 391658344.49, "UT_Buy": false, "ST_Trend": 1, "Aroon_Up": 100.0, "UT_Pos": 1, "PSAR_Trend": "Bull", "Pattern_Label": "POP_CEPAT"}, {"Ticker": "ARTO", "Signal_Date": "2025-12-15", "Bars_Ago": 0, "Open": 2000, "Close": 2220, "Pct_Change_Price": 11.0, "Volume": 54620100, "Volume_Spike": true, "KO": 134649189.74, "UT_Buy": true, "ST_Trend": 1, "Aroon_Up": 100.0, "UT_Pos": 1, "PSAR_Trend": "Bull", "Pattern_Label": "RUNNER"}, {"Ticker": "TUGU", "Signal_Date": "2025-12-15", "Bars_Ago": 0, "Open": 1095, "Close": 1165, "Pct_Change_Price": 7.87, "Volume": 22518600, "Volume_Spike": true, "KO": 43169302.26, "UT_Buy": true, "ST_Trend": 1, "Aroon_Up": 100.0, "UT_Pos": 1, "PSAR_Trend": "Bull", "Pattern_Label": "RUNNER"}, {"Ticker": "ESSA", "Signal_Date": "2025-12-15", "Bars_Ago": 0, "Open": 610, "Close": 655, "Pct_Change_Price": 7.38, "Volume": 104034300, "Volume_Spike": true, "KO": -58243525.59, "UT_Buy": true, "ST_Trend": 1, "Aroon_Up": 100.0, "UT_Pos": 1, "PSAR_Trend": "Bull", "Pattern_Label": "RUNNER"}, {"Ticker": "APLN", "Signal_Date": "2025-12-15", "Bars_Ago": 0, "Open": 103, "Close": 108, "Pct_Change_Price": 5.88, "Volume": 89615000, "Volume_Spike": true, "KO": 259282759.55, "UT_Buy": true, "ST_Trend": 1, "Aroon_Up": 100.0, "UT_Pos": 1, "PSAR_Trend": "Bull", "Pattern_Label": "RUNNER"}, {"Ticker": "ESTA", "Signal_Date": "2025-12-15", "Bars_Ago": 0, "Open": 250, "Close": 260, "Pct_Change_Price": 5.69, "Volume": 18955100, "Volume_Spike": true, "KO": -63481995.49, "UT_Buy": false, "ST_Trend": 1, "Aroon_Up": 100.0, "UT_Pos": 1, "PSAR_Trend": "Bull", "Pattern_Label": "RUNNER"}, {"Ticker": "TOWR", "Signal_Date": "2025-12-15", "Bars_Ago": 0, "Open": 540, "Close": 570, "Pct_Change_Price": 5.56, "Volume": 39206100, "Volume_Spike": true, "KO": -98653009.16, "UT_Buy": true, "ST_Trend": -1, "Aroon_Up": 100.0, "UT_Pos": 1, "PSAR_Trend": "Bull", "Pattern_Label": "POP_CEPAT"}, {"Ticker": "HATM", "Signal_Date": "2025-12-15", "Bars_Ago": 0, "Open": 396, "Close": 418, "Pct_Change_Price": 5.56, "Volume": 88927400, "Volume_Spike": true, "KO": 395616246.33, "UT_Buy": false, "ST_Trend": 1, "Aroon_Up": 100.0, "UT_Pos": 1, "PSAR_Trend": "Bull", "Pattern_Label": "RUNNER"}, {"Ticker": "BBNI", "Signal_Date": "2025-12-15", "Bars_Ago": 0, "Open": 4270, "Close": 4440, "Pct_Change_Price": 4.72, "Volume": 57531500, "Volume_Spike": true, "KO": -90233686.62, "UT_Buy": true, "ST_Trend": 1, "Aroon_Up": 100.0, "UT_Pos": 1, "PSAR_Trend": "Bull", "Pattern_Label": "RUNNER"}, {"Ticker": "MDKA", "Signal_Date": "2025-12-15", "Bars_Ago": 0, "Open": 2280, "Close": 2350, "Pct_Change_Price": 4.44, "Volume": 153363100, "Volume_Spike": true, "KO": 270550093.36, "UT_Buy": true, "ST_Trend": -1, "Aroon_Up": 100.0, "UT_Pos": 1, "PSAR_Trend": "Bull", "Pattern_Label": "NOISE_TRAP"}, {"Ticker": "TINS", "Signal_Date": "2025-12-15", "Bars_Ago": 0, "Open": 3430, "Close": 3550, "Pct_Change_Price": 4.41, "Volume": 171210100, "Volume_Spike": true, "KO": -194248846.15, "UT_Buy": false, "ST_Trend": 1, "Aroon_Up": 100.0, "UT_Pos": 1, "PSAR_Trend": "Bull", "Pattern_Label": "RUNNER"}, {"Ticker": "SIDO", "Signal_Date": "2025-12-15", "Bars_Ago": 0, "Open": 535, "Close": 550, "Pct_Change_Price": 3.77, "Volume": 40698400, "Volume_Spike": true, "KO": -24024152.87, "UT_Buy": true, "ST_Trend": -1, "Aroon_Up": 100.0, "UT_Pos": 1, "PSAR_Trend": "Bull", "Pattern_Label": "NOISE_TRAP"}, {"Ticker": "BBHI", "Signal_Date": "2025-12-15", "Bars_Ago": 0, "Open": 1485, "Close": 1535, "Pct_Change_Price": 3.72, "Volume": 5545900, "Volume_Spike": true, "KO": 8007504.95, "UT_Buy": true, "ST_Trend": 1, "Aroon_Up": 100.0, "UT_Pos": 1, "PSAR_Trend": "Bull", "Pattern_Label": "RUNNER"}, {"Ticker": "CRSN", "Signal_Date": "2025-12-15", "Bars_Ago": 0, "Open": 130, "Close": 135, "Pct_Change_Price": 3.05, "Volume": 196785700, "Volume_Spike": true, "KO": 367573545.48, "UT_Buy": false, "ST_Trend": 1, "Aroon_Up": 100.0, "UT_Pos": -1, "PSAR_Trend": "Bull", "Pattern_Label": "UNCLASSIFIED"}, {"Ticker": "IPCC", "Signal_Date": "2025-12-15", "Bars_Ago": 0, "Open": 1390, "Close": 1420, "Pct_Change_Price": 2.9, "Volume": 6428200, "Volume_Spike": true, "KO": 32903287.98, "UT_Buy": false, "ST_Trend": 1, "Aroon_Up": 100.0, "UT_Pos": 1, "PSAR_Trend": "Bull", "Pattern_Label": "RUNNER"}, {"Ticker": "TSPC", "Signal_Date": "2025-12-15", "Bars_Ago": 0, "Open": 2790, "Close": 2840, "Pct_Change_Price": 2.53, "Volume": 1581000, "Volume_Spike": true, "KO": 1039627.46, "UT_Buy": false, "ST_Trend": -1, "Aroon_Up": 100.0, "UT_Pos": 1, "PSAR_Trend": "Bull", "Pattern_Label": "NOISE_TRAP"}, {"Ticker": "KPIG", "Signal_Date": "2025-12-15", "Bars_Ago": 0, "Open": 135, "Close": 137, "Pct_Change_Price": 2.24, "Volume": 164410300, "Volume_Spike": true, "KO": -496633493.55, "UT_Buy": false, "ST_Trend": -1, "Aroon_Up": 100.0, "UT_Pos": 1, "PSAR_Trend": "Bull", "Pattern_Label": "NOISE_TRAP"}, {"Ticker": "BBRI", "Signal_Date": "2025-12-15", "Bars_Ago": 0, "Open": 3650, "Close": 3780, "Pct_Change_Price": 4.13, "Volume": 312694100, "Volume_Spike": false, "KO": -381546758.95, "UT_Buy": true, "ST_Trend": -1, "Aroon_Up": 100.0, "UT_Pos": 1, "PSAR_Trend": "Bull", "Pattern_Label": "NOISE_TRAP"}, {"Ticker": "OASA", "Signal_Date": "2025-12-15", "Bars_Ago": 0, "Open": 230, "Close": 230, "Pct_Change_Price": 1.77, "Volume": 136797200, "Volume_Spike": false, "KO": 182082939.87, "UT_Buy": false, "ST_Trend": -1, "Aroon_Up": 87.5, "UT_Pos": -1, "PSAR_Trend": "Bull", "Pattern_Label": "NOISE_TRAP"}, {"Ticker": "AIMS", "Signal_Date": "2025-12-15", "Bars_Ago": 0, "Open": 438, "Close": 398, "Pct_Change_Price": -8.72, "Volume": 1533300, "Volume_Spike": false, "KO": 6858452.73, "UT_Buy": false, "ST_Trend": -1, "Aroon_Up": 50.0, "UT_Pos": -1, "PSAR_Trend": "Bull", "Pattern_Label": "NOISE_TRAP"}, {"Ticker": "BRMS", "Signal_Date": "2025-12-12", "Bars_Ago": 1, "Open": 1015, "Close": 1230, "Pct_Change_Price": 24.87, "Volume": 2563550200, "Volume_Spike": true, "KO": 4111186718.82, "UT_Buy": true, "ST_Trend": 1, "Aroon_Up": 100.0, "UT_Pos": 1, "PSAR_Trend": "Bull", "Pattern_Label": "POP_CEPAT"}, {"Ticker": "HRTA", "Signal_Date": "2025-12-12", "Bars_Ago": 1, "Open": 1495, "Close": 1800, "Pct_Change_Price": 23.71, "Volume": 180861100, "Volume_Spike": true, "KO": 24799786.39, "UT_Buy": true, "ST_Trend": 1, "Aroon_Up": 100.0, "UT_Pos": 1, "PSAR_Trend": "Bull", "Pattern_Label": "POP_CEPAT"}, {"Ticker": "PSAB", "Signal_Date": "2025-12-12", "Bars_Ago": 1, "Open": 555, "Close": 605, "Pct_Change_Price": 11.01, "Volume": 610171200, "Volume_Spike": true, "KO": -103227272.74, "UT_Buy": false, "ST_Trend": 1, "Aroon_Up": 100.0, "UT_Pos": 1, "PSAR_Trend": "Bull", "Pattern_Label": "RUNNER"}, {"Ticker": "ARKO", "Signal_Date": "2025-12-12", "Bars_Ago": 1, "Open": 5150, "Close": 5150, "Pct_Change_Price": 9.57, "Volume": 21273400, "Volume_Spike": true, "KO": 54006514.18, "UT_Buy": false, "ST_Trend": 1, "Aroon_Up": 100.0, "UT_Pos": 1, "PSAR_Trend": "Bull", "Pattern_Label": "RUNNER"}, {"Ticker": "AMMN", "Signal_Date": "2025-12-12", "Bars_Ago": 1, "Open": 6350, "Close": 6725, "Pct_Change_Price": 5.91, "Volume": 59828400, "Volume_Spike": true, "KO": 184054771.5, "UT_Buy": true, "ST_Trend": -1, "Aroon_Up": 100.0, "UT_Pos": 1, "PSAR_Trend": "Bull", "Pattern_Label": "POP_CEPAT"}, {"Ticker": "ANTM", "Signal_Date": "2025-12-12", "Bars_Ago": 1, "Open": 2910, "Close": 3050, "Pct_Change_Price": 5.54, "Volume": 304157500, "Volume_Spike": true, "KO": -40142072.27, "UT_Buy": true, "ST_Trend": -1, "Aroon_Up": 100.0, "UT_Pos": 1, "PSAR_Trend": "Bull", "Pattern_Label": "POP_CEPAT"}, {"Ticker": "KSIX", "Signal_Date": "2025-12-12", "Bars_Ago": 1, "Open": 390, "Close": 406, "Pct_Change_Price": 4.1, "Volume": 8342100, "Volume_Spike": true, "KO": 19511626.46, "UT_Buy": false, "ST_Trend": 1, "Aroon_Up": 100.0, "UT_Pos": 1, "PSAR_Trend": "Bull", "Pattern_Label": "RUNNER"}, {"Ticker": "FITT", "Signal_Date": "2025-12-12", "Bars_Ago": 1, "Open": 860, "Close": 695, "Pct_Change_Price": -1.42, "Volume": 6024500, "Volume_Spike": true, "KO": 11988544.21, "UT_Buy": false, "ST_Trend": -1, "Aroon_Up": 100.0, "UT_Pos": 1, "PSAR_Trend": "Bull", "Pattern_Label": "NOISE_TRAP"}, {"Ticker": "NIRO", "Signal_Date": "2025-12-12", "Bars_Ago": 1, "Open": 322, "Close": 310, "Pct_Change_Price": -3.12, "Volume": 12423000, "Volume_Spike": true, "KO": 5436775.68, "UT_Buy": false, "ST_Trend": -1, "Aroon_Up": 37.5, "UT_Pos": -1, "PSAR_Trend": "Bull", "Pattern_Label": "NOISE_TRAP"}, {"Ticker": "INDX", "Signal_Date": "2025-12-12", "Bars_Ago": 1, "Open": 222, "Close": 171, "Pct_Change_Price": -13.64, "Volume": 222276200, "Volume_Spike": true, "KO": 363448979.23, "UT_Buy": false, "ST_Trend": 1, "Aroon_Up": 100.0, "UT_Pos": -1, "PSAR_Trend": "Bull", "Pattern_Label": "UNCLASSIFIED"}]}