{"last_update": "2026-04-16 17:00:00 WIB (Backfilled)", "super_screener": [{"Ticker": "AYLS", "Signal_Date": "2026-04-16", "Bars_Ago": 0, "Open": 177, "Close": 228, "Pct_Change_Price": 29.55, "Volume": 72190000, "Volume_Spike": true, "KO": 135133950.78, "UT_Buy": true, "ST_Trend": -1, "Aroon_Up": 100.0, "UT_Pos": 1, "PSAR_Trend": "Bear", "Pattern_Label": "POP_CEPAT", "PER": "N/A", "PBV": "N/A"}, {"Ticker": "OLIV", "Signal_Date": "2026-04-16", "Bars_Ago": 0, "Open": 55, "Close": 61, "Pct_Change_Price": 8.93, "Volume": 15050100, "Volume_Spike": true, "KO": 127255644.96, "UT_Buy": true, "ST_Trend": -1, "Aroon_Up": 100.0, "UT_Pos": 1, "PSAR_Trend": "Bear", "Pattern_Label": "POP_CEPAT", "PER": "N/A", "PBV": "N/A"}, {"Ticker": "MTDL", "Signal_Date": "2026-04-16", "Bars_Ago": 0, "Open": 585, "Close": 595, "Pct_Change_Price": 1.71, "Volume": 2660400, "Volume_Spike": true, "KO": 31046158.54, "UT_Buy": true, "ST_Trend": -1, "Aroon_Up": 100.0, "UT_Pos": 1, "PSAR_Trend": "Bull", "Pattern_Label": "NOISE_TRAP", "PER": "N/A", "PBV": "N/A"}], "aroon_ut": [{"Ticker": "AYLS", "Signal_Date": "2026-04-16", "Bars_Ago": 0, "Open": 177, "Close": 228, "Pct_Change_Price": 29.55, "Volume": 72190000, "Volume_Spike": true, "KO": 135133950.78, "UT_Buy": true, "ST_Trend": -1, "Aroon_Up": 100.0, "UT_Pos": 1, "PSAR_Trend": "Bear", "Pattern_Label": "POP_CEPAT", "PER": "N/A", "PBV": "N/A"}, {"Ticker": "SMDM", "Signal_Date": "2026-04-16", "Bars_Ago": 0, "Open": 590, "Close": 730, "Pct_Change_Price": 24.79, "Volume": 2367900, "Volume_Spike": true, "KO": 585338.95, "UT_Buy": true, "ST_Trend": 1, "Aroon_Up": 100.0, "UT_Pos": 1, "PSAR_Trend": "Bull", "Pattern_Label": "POP_CEPAT", "PER": "N/A", "PBV": "N/A"}, {"Ticker": "OLIV", "Signal_Date": "2026-04-16", "Bars_Ago": 0, "Open": 55, "Close": 61, "Pct_Change_Price": 8.93, "Volume": 15050100, "Volume_Spike": true, "KO": 127255644.96, "UT_Buy": true, "ST_Trend": -1, "Aroon_Up": 100.0, "UT_Pos": 1, "PSAR_Trend": "Bear", "Pattern_Label": "POP_CEPAT", "PER": "N/A", "PBV": "N/A"}, {"Ticker": "MARI", "Signal_Date": "2026-04-16", "Bars_Ago": 0, "Open": 28, "Close": 30, "Pct_Change_Price": 7.14, "Volume": 3648800, "Volume_Spike": true, "KO": -11673767.5, "UT_Buy": true, "ST_Trend": -1, "Aroon_Up": 100.0, "UT_Pos": 1, "PSAR_Trend": "Bear", "Pattern_Label": "POP_CEPAT", "PER": "N/A", "PBV": "N/A"}, {"Ticker": "WOMF", "Signal_Date": "2026-04-16", "Bars_Ago": 0, "Open": 294, "Close": 308, "Pct_Change_Price": 4.76, "Volume": 1239800, "Volume_Spike": true, "KO": 4286872.62, "UT_Buy": true, "ST_Trend": -1, "Aroon_Up": 100.0, "UT_Pos": 1, "PSAR_Trend": "Bull", "Pattern_Label": "NOISE_TRAP", "PER": "N/A", "PBV": "N/A"}, {"Ticker": "SMGR", "Signal_Date": "2026-04-16", "Bars_Ago": 0, "Open": 2420, "Close": 2490, "Pct_Change_Price": 3.75, "Volume": 17439100, "Volume_Spike": true, "KO": 42374585.56, "UT_Buy": true, "ST_Trend": -1, "Aroon_Up": 100.0, "UT_Pos": 1, "PSAR_Trend": "Bull", "Pattern_Label": "NOISE_TRAP", "PER": "N/A", "PBV": "N/A"}, {"Ticker": "AMAR", "Signal_Date": "2026-04-16", "Bars_Ago": 0, "Open": 197, "Close": 202, "Pct_Change_Price": 3.06, "Volume": 930000, "Volume_Spike": true, "KO": -7288155.37, "UT_Buy": true, "ST_Trend": -1, "Aroon_Up": 100.0, "UT_Pos": 1, "PSAR_Trend": "Bull", "Pattern_Label": "NOISE_TRAP", "PER": "N/A", "PBV": "N/A"}, {"Ticker": "CMPP", "Signal_Date": "2026-04-16", "Bars_Ago": 0, "Open": 83, "Close": 85, "Pct_Change_Price": 2.41, "Volume": 142800, "Volume_Spike": true, "KO": 142788.17, "UT_Buy": true, "ST_Trend": -1, "Aroon_Up": 100.0, "UT_Pos": 1, "PSAR_Trend": "Bear", "Pattern_Label": "NOISE_TRAP", "PER": "N/A", "PBV": "N/A"}, {"Ticker": "MTDL", "Signal_Date": "2026-04-16", "Bars_Ago": 0, "Open": 585, "Close": 595, "Pct_Change_Price": 1.71, "Volume": 2660400, "Volume_Spike": true, "KO": 31046158.54, "UT_Buy": true, "ST_Trend": -1, "Aroon_Up": 100.0, "UT_Pos": 1, "PSAR_Trend": "Bull", "Pattern_Label": "NOISE_TRAP", "PER": "N/A", "PBV": "N/A"}, {"Ticker": "MANG", "Signal_Date": "2026-04-16", "Bars_Ago": 0, "Open": 45, "Close": 45, "Pct_Change_Price": 9.76, "Volume": 9614700, "Volume_Spike": false, "KO": -16090388.76, "UT_Buy": true, "ST_Trend": -1, "Aroon_Up": 100.0, "UT_Pos": 1, "PSAR_Trend": "Bull", "Pattern_Label": "NOISE_TRAP", "PER": "N/A", "PBV": "N/A"}, {"Ticker": "TIRT", "Signal_Date": "2026-04-16", "Bars_Ago": 0, "Open": 570, "Close": 600, "Pct_Change_Price": 7.14, "Volume": 320100, "Volume_Spike": false, "KO": -11781118.34, "UT_Buy": true, "ST_Trend": -1, "Aroon_Up": 50.0, "UT_Pos": 1, "PSAR_Trend": "Bull", "Pattern_Label": "NOISE_TRAP", "PER": "N/A", "PBV": "N/A"}, {"Ticker": "DIGI", "Signal_Date": "2026-04-16", "Bars_Ago": 0, "Open": 34, "Close": 34, "Pct_Change_Price": 6.25, "Volume": 678000, "Volume_Spike": false, "KO": -13056343.29, "UT_Buy": true, "ST_Trend": -1, "Aroon_Up": 50.0, "UT_Pos": 1, "PSAR_Trend": "Bull", "Pattern_Label": "NOISE_TRAP", "PER": 0.0, "PBV": -0.0}, {"Ticker": "TARA", "Signal_Date": "2026-04-16", "Bars_Ago": 0, "Open": 30, "Close": 31, "Pct_Change_Price": 3.33, "Volume": 448500, "Volume_Spike": false, "KO": -7455501.91, "UT_Buy": true, "ST_Trend": -1, "Aroon_Up": 100.0, "UT_Pos": 1, "PSAR_Trend": "Bear", "Pattern_Label": "NOISE_TRAP", "PER": -3.87, "PBV": 1.47}, {"Ticker": "PSSI", "Signal_Date": "2026-04-16", "Bars_Ago": 0, "Open": 342, "Close": 350, "Pct_Change_Price": 2.94, "Volume": 191800, "Volume_Spike": false, "KO": -1648704.7, "UT_Buy": true, "ST_Trend": -1, "Aroon_Up": 100.0, "UT_Pos": 1, "PSAR_Trend": "Bear", "Pattern_Label": "NOISE_TRAP", "PER": "N/A", "PBV": "N/A"}, {"Ticker": "ACES", "Signal_Date": "2026-04-16", "Bars_Ago": 0, "Open": 362, "Close": 366, "Pct_Change_Price": 2.23, "Volume": 38249400, "Volume_Spike": false, "KO": 370726590.87, "UT_Buy": true, "ST_Trend": -1, "Aroon_Up": 100.0, "UT_Pos": 1, "PSAR_Trend": "Bear", "Pattern_Label": "NOISE_TRAP", "PER": 22.77, "PBV": "N/A"}, {"Ticker": "MTEL", "Signal_Date": "2026-04-16", "Bars_Ago": 0, "Open": 530, "Close": 535, "Pct_Change_Price": 0.94, "Volume": 2215600, "Volume_Spike": false, "KO": 83092407.84, "UT_Buy": true, "ST_Trend": -1, "Aroon_Up": 87.5, "UT_Pos": 1, "PSAR_Trend": "Bull", "Pattern_Label": "NOISE_TRAP", "PER": "N/A", "PBV": "N/A"}], "ko_ut_vol": [{"Ticker": "AYLS", "Signal_Date": "2026-04-16", "Bars_Ago": 0, "Open": 177, "Close": 228, "Pct_Change_Price": 29.55, "Volume": 72190000, "Volume_Spike": true, "KO": 135133950.78, "UT_Buy": true, "ST_Trend": -1, "Aroon_Up": 100.0, "UT_Pos": 1, "PSAR_Trend": "Bear", "Pattern_Label": "POP_CEPAT", "PER": "N/A", "PBV": "N/A"}, {"Ticker": "OLIV", "Signal_Date": "2026-04-16", "Bars_Ago": 0, "Open": 55, "Close": 61, "Pct_Change_Price": 8.93, "Volume": 15050100, "Volume_Spike": true, "KO": 127255644.96, "UT_Buy": true, "ST_Trend": -1, "Aroon_Up": 100.0, "UT_Pos": 1, "PSAR_Trend": "Bear", "Pattern_Label": "POP_CEPAT", "PER": "N/A", "PBV": "N/A"}, {"Ticker": "PLAN", "Signal_Date": "2026-04-16", "Bars_Ago": 0, "Open": 52, "Close": 52, "Pct_Change_Price": 8.33, "Volume": 23226100, "Volume_Spike": true, "KO": -79842307.46, "UT_Buy": true, "ST_Trend": -1, "Aroon_Up": 62.5, "UT_Pos": 1, "PSAR_Trend": "Bull", "Pattern_Label": "POP_CEPAT", "PER": "N/A", "PBV": "N/A"}, {"Ticker": "MTDL", "Signal_Date": "2026-04-16", "Bars_Ago": 0, "Open": 585, "Close": 595, "Pct_Change_Price": 1.71, "Volume": 2660400, "Volume_Spike": true, "KO": 31046158.54, "UT_Buy": true, "ST_Trend": -1, "Aroon_Up": 100.0, "UT_Pos": 1, "PSAR_Trend": "Bull", "Pattern_Label": "NOISE_TRAP", "PER": "N/A", "PBV": "N/A"}], "aroon_psar": [{"Ticker": "SMDM", "Signal_Date": "2026-04-16", "Bars_Ago": 0, "Open": 590, "Close": 730, "Pct_Change_Price": 24.79, "Volume": 2367900, "Volume_Spike": true, "KO": 585338.95, "UT_Buy": true, "ST_Trend": 1, "Aroon_Up": 100.0, "UT_Pos": 1, "PSAR_Trend": "Bull", "Pattern_Label": "POP_CEPAT", "PER": "N/A", "PBV": "N/A"}, {"Ticker": "SGER", "Signal_Date": "2026-04-16", "Bars_Ago": 0, "Open": 406, "Close": 434, "Pct_Change_Price": 8.5, "Volume": 13039400, "Volume_Spike": true, "KO": -467851418.84, "UT_Buy": false, "ST_Trend": -1, "Aroon_Up": 100.0, "UT_Pos": 1, "PSAR_Trend": "Bull", "Pattern_Label": "POP_CEPAT", "PER": "N/A", "PBV": 0.0}, {"Ticker": "WINR", "Signal_Date": "2026-04-16", "Bars_Ago": 0, "Open": 39, "Close": 39, "Pct_Change_Price": 8.33, "Volume": 47455100, "Volume_Spike": true, "KO": 234295313.25, "UT_Buy": false, "ST_Trend": 1, "Aroon_Up": 100.0, "UT_Pos": 1, "PSAR_Trend": "Bull", "Pattern_Label": "RUNNER", "PER": "N/A", "PBV": -0.0}, {"Ticker": "NAYZ", "Signal_Date": "2026-04-16", "Bars_Ago": 0, "Open": 68, "Close": 72, "Pct_Change_Price": 5.88, "Volume": 29196400, "Volume_Spike": true, "KO": 126093228.22, "UT_Buy": false, "ST_Trend": -1, "Aroon_Up": 100.0, "UT_Pos": 1, "PSAR_Trend": "Bull", "Pattern_Label": "POP_CEPAT", "PER": "N/A", "PBV": "N/A"}, {"Ticker": "WSBP", "Signal_Date": "2026-04-16", "Bars_Ago": 0, "Open": 20, "Close": 20, "Pct_Change_Price": 5.26, "Volume": 75087300, "Volume_Spike": true, "KO": 287475944.71, "UT_Buy": false, "ST_Trend": -1, "Aroon_Up": 100.0, "UT_Pos": 1, "PSAR_Trend": "Bull", "Pattern_Label": "POP_CEPAT", "PER": "N/A", "PBV": "N/A"}, {"Ticker": "WOMF", "Signal_Date": "2026-04-16", "Bars_Ago": 0, "Open": 294, "Close": 308, "Pct_Change_Price": 4.76, "Volume": 1239800, "Volume_Spike": true, "KO": 4286872.62, "UT_Buy": true, "ST_Trend": -1, "Aroon_Up": 100.0, "UT_Pos": 1, "PSAR_Trend": "Bull", "Pattern_Label": "NOISE_TRAP", "PER": "N/A", "PBV": "N/A"}, {"Ticker": "WGSH", "Signal_Date": "2026-04-16", "Bars_Ago": 0, "Open": 135, "Close": 135, "Pct_Change_Price": 4.65, "Volume": 1858300, "Volume_Spike": true, "KO": -1584266.54, "UT_Buy": false, "ST_Trend": -1, "Aroon_Up": 100.0, "UT_Pos": 1, "PSAR_Trend": "Bull", "Pattern_Label": "NOISE_TRAP", "PER": "N/A", "PBV": "N/A"}, {"Ticker": "SMGR", "Signal_Date": "2026-04-16", "Bars_Ago": 0, "Open": 2420, "Close": 2490, "Pct_Change_Price": 3.75, "Volume": 17439100, "Volume_Spike": true, "KO": 42374585.56, "UT_Buy": true, "ST_Trend": -1, "Aroon_Up": 100.0, "UT_Pos": 1, "PSAR_Trend": "Bull", "Pattern_Label": "NOISE_TRAP", "PER": "N/A", "PBV": "N/A"}, {"Ticker": "AMAR", "Signal_Date": "2026-04-16", "Bars_Ago": 0, "Open": 197, "Close": 202, "Pct_Change_Price": 3.06, "Volume": 930000, "Volume_Spike": true, "KO": -7288155.37, "UT_Buy": true, "ST_Trend": -1, "Aroon_Up": 100.0, "UT_Pos": 1, "PSAR_Trend": "Bull", "Pattern_Label": "NOISE_TRAP", "PER": "N/A", "PBV": "N/A"}, {"Ticker": "MTDL", "Signal_Date": "2026-04-16", "Bars_Ago": 0, "Open": 585, "Close": 595, "Pct_Change_Price": 1.71, "Volume": 2660400, "Volume_Spike": true, "KO": 31046158.54, "UT_Buy": true, "ST_Trend": -1, "Aroon_Up": 100.0, "UT_Pos": 1, "PSAR_Trend": "Bull", "Pattern_Label": "NOISE_TRAP", "PER": "N/A", "PBV": "N/A"}, {"Ticker": "TLDN", "Signal_Date": "2026-04-16", "Bars_Ago": 0, "Open": 645, "Close": 650, "Pct_Change_Price": 0.78, "Volume": 2040200, "Volume_Spike": true, "KO": 6923925.53, "UT_Buy": false, "ST_Trend": -1, "Aroon_Up": 100.0, "UT_Pos": 1, "PSAR_Trend": "Bull", "Pattern_Label": "NOISE_TRAP", "PER": "N/A", "PBV": -0.02}, {"Ticker": "JAWA", "Signal_Date": "2026-04-16", "Bars_Ago": 0, "Open": 160, "Close": 160, "Pct_Change_Price": -0.62, "Volume": 2298600, "Volume_Spike": true, "KO": -34750845.94, "UT_Buy": false, "ST_Trend": -1, "Aroon_Up": 37.5, "UT_Pos": 1, "PSAR_Trend": "Bull", "Pattern_Label": "NOISE_TRAP", "PER": "N/A", "PBV": "N/A"}, {"Ticker": "DGNS", "Signal_Date": "2026-04-16", "Bars_Ago": 0, "Open": 290, "Close": 288, "Pct_Change_Price": -1.37, "Volume": 951800, "Volume_Spike": true, "KO": -59714787.94, "UT_Buy": false, "ST_Trend": -1, "Aroon_Up": 62.5, "UT_Pos": 1, "PSAR_Trend": "Bull", "Pattern_Label": "NOISE_TRAP", "PER": "N/A", "PBV": "N/A"}, {"Ticker": "BEER", "Signal_Date": "2026-04-16", "Bars_Ago": 0, "Open": 161, "Close": 151, "Pct_Change_Price": -6.79, "Volume": 281854400, "Volume_Spike": true, "KO": 873092584.82, "UT_Buy": false, "ST_Trend": -1, "Aroon_Up": 100.0, "UT_Pos": 1, "PSAR_Trend": "Bull", "Pattern_Label": "NOISE_TRAP", "PER": "N/A", "PBV": "N/A"}, {"Ticker": "PSAB", "Signal_Date": "2026-04-16", "Bars_Ago": 0, "Open": 530, "Close": 565, "Pct_Change_Price": 7.62, "Volume": 120898600, "Volume_Spike": false, "KO": 374030265.39, "UT_Buy": false, "ST_Trend": -1, "Aroon_Up": 100.0, "UT_Pos": 1, "PSAR_Trend": "Bull", "Pattern_Label": "NOISE_TRAP", "PER": "N/A", "PBV": "N/A"}, {"Ticker": "RBMS", "Signal_Date": "2026-04-16", "Bars_Ago": 0, "Open": 59, "Close": 60, "Pct_Change_Price": 3.45, "Volume": 8508300, "Volume_Spike": false, "KO": 30881667.45, "UT_Buy": false, "ST_Trend": -1, "Aroon_Up": 100.0, "UT_Pos": 1, "PSAR_Trend": "Bull", "Pattern_Label": "NOISE_TRAP", "PER": "N/A", "PBV": "N/A"}, {"Ticker": "PMUI", "Signal_Date": "2026-04-16", "Bars_Ago": 0, "Open": 105, "Close": 107, "Pct_Change_Price": 2.88, "Volume": 6668600, "Volume_Spike": false, "KO": 71355103.64, "UT_Buy": false, "ST_Trend": -1, "Aroon_Up": 37.5, "UT_Pos": 1, "PSAR_Trend": "Bull", "Pattern_Label": "NOISE_TRAP", "PER": "N/A", "PBV": "N/A"}, {"Ticker": "BATR", "Signal_Date": "2026-04-16", "Bars_Ago": 0, "Open": 96, "Close": 96, "Pct_Change_Price": 0.0, "Volume": 8018500, "Volume_Spike": false, "KO": 66436427.27, "UT_Buy": false, "ST_Trend": -1, "Aroon_Up": 100.0, "UT_Pos": 1, "PSAR_Trend": "Bull", "Pattern_Label": "NOISE_TRAP", "PER": "N/A", "PBV": "N/A"}, {"Ticker": "WINE", "Signal_Date": "2026-04-16", "Bars_Ago": 0, "Open": 183, "Close": 183, "Pct_Change_Price": 0.0, "Volume": 2026600, "Volume_Spike": false, "KO": 20537653.41, "UT_Buy": false, "ST_Trend": -1, "Aroon_Up": 100.0, "UT_Pos": 1, "PSAR_Trend": "Bull", "Pattern_Label": "NOISE_TRAP", "PER": "N/A", "PBV": "N/A"}, {"Ticker": "INDO", "Signal_Date": "2026-04-16", "Bars_Ago": 0, "Open": 168, "Close": 167, "Pct_Change_Price": -0.6, "Volume": 14069200, "Volume_Spike": false, "KO": -104405570.4, "UT_Buy": false, "ST_Trend": -1, "Aroon_Up": 62.5, "UT_Pos": 1, "PSAR_Trend": "Bull", "Pattern_Label": "NOISE_TRAP", "PER": -5.07, "PBV": 2.39}, {"Ticker": "TAMA", "Signal_Date": "2026-04-16", "Bars_Ago": 0, "Open": 191, "Close": 158, "Pct_Change_Price": -9.2, "Volume": 11065300, "Volume_Spike": false, "KO": -56160448.52, "UT_Buy": false, "ST_Trend": 1, "Aroon_Up": 100.0, "UT_Pos": -1, "PSAR_Trend": "Bull", "Pattern_Label": "UNCLASSIFIED", "PER": "N/A", "PBV": "N/A"}]}